Workbook
Name BuiltIn_Print_Area: #REF!
Name BuiltIn_Print_Area: #REF!
Name BuiltIn_Print_Area: #REF!
Name BuiltIn_Print_Area: #REF!
Name BuiltIn_Print_Area___0: #REF!
Name BuiltIn_Print_Area___0: #REF!
Name BuiltIn_Print_Area___0: #REF!
Name BuiltIn_Print_Area___0___0: #REF!
Name BuiltIn_Print_Area___0___0___0: #REF!
Name BuiltIn_Print_Area___0___0___0___0: #REF!
Name BuiltIn_Print_Area___0___0___0___0___0: #REF!
Name BuiltIn_Print_Titles: #REF!
Name BuiltIn_Print_Titles___0: NA()
Name BuiltIn_Print_Titles___0___0: #REF!
Name BuiltIn_Print_Titles___0___0___0: #REF!
Name BuiltIn_Print_Titles___0___0___0___0: NA()
Name LAN: #REF!
Name PP: #REF!
Name UnitType2: #REF!
Name UnitType2: #REF!
Name URURU: #REF!
Name URURU: #REF!
Name Validation_Equipment: OFFSET('[1]EQUIPMENT DYNAMIC LIST'!$N$2,,,COUNTIF('[1]EQUIPMENT DYNAMIC LIST'!$N$2:$N$500,"?*"))
Name Validation_Fans: OFFSET('[1]FAN DYNAMIC LIST'!$Q$2,,,COUNTIF('[1]FAN DYNAMIC LIST'!$Q$2:$Q$1000,"?*"))
Name Validation_Heaters: OFFSET('[1]HEATER DYNAMIC LIST'!$Q$2,,,COUNTIF('[1]HEATER DYNAMIC LIST'!$Q$2:$Q$1000,"?*"))
Name Validation_MiniSplit: OFFSET('[1]MINI SPLIT DYNAMIC LIST'!$Q$2,,,COUNTIF('[1]MINI SPLIT DYNAMIC LIST'!$Q$2:$Q$1000,"?*"))
Name Validation_PTAC: OFFSET('[1]PTAC DYNAMIC LIST'!$Q$2,,,COUNTIF('[1]PTAC DYNAMIC LIST'!$Q$2:$Q$1000,"?*"))
Name Validation_Thermstats: OFFSET('[1]THERMOSTAT DYNAMIC LIST'!$M$2,,,COUNTIF('[1]THERMOSTAT DYNAMIC LIST'!$M$2:$M$500,"?*"))

Sheet SUMMARY
A2: GC LEGACY CONSTRUCTION
B6: Proposal Date:
B7: =+'BREAKDOWN (BUILDING)'!C1 -> Project Name: University Park Village (Starbucks 6212)
B8: =+A2 -> GC LEGACY CONSTRUCTION
B9: =+'BREAKDOWN (BUILDING)'!C3 -> Plan Date: 8/27/2025
A11: PROJECT PROPOSAL
A12: ITEM | C12: DESCRIPTION | K12: QUANTITY | L12: UOM | M12: LABOR HOURS | N12: TOTAL LABOUR (US$) | O12: TOTAL MATERIAL (US$) | P12: TOTAL AMOUNT(US$)
A14: I. | C14: MATERIALS
E15: ELECTRICAL WORKS
D16: A. | E16: SITE WORKS (not in scope) | O16: =+'BREAKDOWN (SITE)'!T12 -> 0 | P16: =+N16+O16 -> 0
D18: B. | E18: MATERIAL (NON-QUOTED)
D19: 1 | E19: =+'BREAKDOWN (BUILDING)'!C8 -> Feeders | K19: 1 | L19: lot | O19: ='BREAKDOWN (BUILDING)'!T16 -> 0 | P19: =+N19+O19 -> 0
D20: 2 | E20: =+'BREAKDOWN (BUILDING)'!C18 -> Power Supply for Lighting and Small Power | K20: 1 | L20: lot | O20: =+'BREAKDOWN (BUILDING)'!T49 -> 9217.2023 | P20: =+N20+O20 -> 9217.2023
D21: 3 | E21: =+'BREAKDOWN (BUILDING)'!C51 -> Low Voltage System | K21: 1 | L21: lot | O21: ='BREAKDOWN (BUILDING)'!T58 -> 238.1868 | P21: =+N21+O21 -> 238.1868
D22: 4 | E22: Testing and Commissioning | K22: 1 | L22: lot | O22: 1500 | P22: =+N22+O22 -> 1500
D24: C. | E24: MATERIAL (QUOTED)
D25: 1 | E25: =+'BREAKDOWN (BUILDING)'!C61 -> Panelboards and Equipments | K25: 1 | L25: lot | O25: ='BREAKDOWN (BUILDING)'!T73 -> 0 | P25: =+N25+O25 -> 0
D26: 2 | E26: =+'BREAKDOWN (BUILDING)'!C74 -> Lighting Fixtures and Lighting Controls (Owner Supplied) | K26: 1 | L26: lot | O26: 0 | P26: =+N26+O26 -> 0
D27: 3 | E27: Others | O27: 0 | P27: =+N27+O27 -> 0
D29: D. | E29: SALES TAX (9.5% of A + B + C) | K29: 1 | L29: lot | O29: 0 | P29: =SUM(P15:P27)*Q29 -> 1040.762 | Q29: 0.095
C31: TOTAL MATERIAL COST | P31: =SUM(P13:P30) -> 11996.151
A33: II. | C33: LABOR
D34: 1 | E34: Direct Labor | M34: =+'BREAKDOWN (BUILDING)'!P108+'BREAKDOWN (SITE)'!P12 -> 797.55 | N34: =+M34*$Q$37 -> 141963.9 | O34: 0 | P34: =+N34+O34 -> 141963.9
D35: 2 | E35: Non Productive Labor (20% of Direct Labor) | M35: =+M34*Q35 -> 159.51 | N35: =+M35*$Q$37 -> 28392.78 | O35: 0 | P35: =+N35+O35 -> 28392.78 | Q35: 0.2
C37: TOTAL LABOR HOURS AND LABOR COST | M37: =SUM(M34:M36) -> 957.06 | P37: =SUM(P34:P36) -> 170356.68 | Q37: 178
A39: III. | C39: DIRECT JOB EXPENSES
D41: 1 | E41: Scissor Lifts | K41: 3 | L41: equipment month | O41: 1000 | P41: =+O41*K41 -> 3000
D42: 2 | E42: Title 24 | K42: 1 | L42: lot | O42: 1500 | P42: =+O42*K42 -> 1500
D43: 3 | E43: Temp Power/Lighting | K43: 1 | L43: lot | O43: 1500 | P43: =+O43*K43 -> 1500
D44: 4 | E44: Hauling Equipment (if needed) | P44: =+O44*K44 -> 0
D45: 5 | E45: Excavation Equipment (if needed) | P45: 0
C47: TOTAL JOB EXPENSES | P47: =SUM(P39:P46) -> 6000
A49: IV. | C49: MISCELLANEOUS
D51: 1 | E51: Demolition, Safe-Off (if needed) | K51: 1 | L51: lot | P51: =+N51+O51 -> 0
C53: TOTAL MISCELLANEOUS | P53: =SUM(P48:P52) -> 0
A55: V. | C55: SUBCONTRACTS, if any | P55: 0
A57: VI. | C57: DIRECT COST (I + II + III + IV + V) | P57: =+P31+P37+P47+P53+P55 -> 188352.83
A59: VII. | C59: COMPANY OVERHEAD (10% OF TOTAL DIRECT COST) | K59: 1 | L59: lot | P59: =+P57*$Q$59 -> 18835.283 | Q59: 0.1
A61: VIII. | C61: COMPANY PROFIT (15% OF TOTAL DIRECT COST) | K61: 1 | L61: lot | P61: =+P57*$Q$61 -> 28252.925 | Q61: 0.15
A63: IX. | C63: BONDS, if any | P63: 0
A65: X. | C65: CONTINGENCY, if any | P65: 0
A67: XI. | C67: BID ALTERNATES, if any | P67: 0
A69: XII. | C69: FINAL BID PRICE (VI + VII + VIII + IX + X + XI) | P69: =+P57+P59+P61+P63+P65+P67 -> 235441.04

Sheet BREAKDOWN (BUILDING)
C1: Project Name: University Park Village (Starbucks 6212)
C2: Address: 1620 S University Dr, Fort Worth, TX 76107 | M2: Labor Rate: | N2: 178 | O2: Per Hour | P2: Source: | Q2: NECA
C3: Plan Date: 8/27/2025
B4: Electrical | C4: Electrical | I4: 1ST FLOOR | K4: ROOF PLAN | N4: TOTAL | P4: Total Labor Hrs | Q4: Labor Hours | R4: Total Labor Cost | S4: Material Pricing | T4: Total Material Pricing | U4: Total | V4: REFERENCE
B5: Item No. | C5: Description | D5: Added Description | I5: Qty | J5: Lin. Ft. | K5: Qty | L5: Lin. Ft. | N5: Qty | O5: Lin. Ft. | V5: LABOR HOURS
C6: MAIN BUILDING ELECTRICAL WORKS | E6: CONTRACTOR | G6: CLIENT / VENDOR
E7: PROVIDE | F7: INSTALL | G7: PROVIDE | H7: INSTALL
B8: A.1 | C8: Feeders
C9: Feeder Wires and Conduit
C10: ='TAKEOFF DETAIL'!B14 -> 1-1/4" EMT Conduit | E10: X | F10: X | J10: ='TAKEOFF DETAIL'!BU14 -> 30 | O10: =J10+L10 -> 30 | P10: =IF(N10>0,N10*Q10,O10*Q10) -> 1.86 | Q10: 0.062 | R10: =P10*$N$2 -> 331.08 | T10: =(N10+O10)*S10 -> 0 | U10: =+R10+T10 -> 331.08 | V10: NECA
C11: ='TAKEOFF DETAIL'!B23 -> Copper Wire, 1#3 AWG | E11: X | F11: X | J11: ='TAKEOFF DETAIL'!BU23 -> 120 | O11: =J11+L11 -> 120 | P11: =IF(N11>0,N11*Q11,O11*Q11) -> 1.8 | Q11: 0.015 | R11: =P11*$N$2 -> 320.4 | T11: =(N11+O11)*S11 -> 0 | U11: =+R11+T11 -> 320.4 | V11: NECA
C12: ='TAKEOFF DETAIL'!B24 -> Copper Wire, 1#8G AWG | E12: X | F12: X | J12: ='TAKEOFF DETAIL'!BU24 -> 40 | O12: =J12+L12 -> 40 | P12: =IF(N12>0,N12*Q12,O12*Q12) -> 0.36 | Q12: 0.009 | R12: =P12*$N$2 -> 64.08 | T12: =(N12+O12)*S12 -> 0 | U12: =+R12+T12 -> 64.08 | V12: NECA
C13: Conduit Fittings, support and Wire connectors | E13: X | F13: X | I13: 1 | N13: =I13+K13 -> 1 | P13: =IF(N13>0,N13*Q13,O13*Q13) -> 0 | R13: =P13*$N$2 -> 0 | T13: =(N13+O13)*S13 -> 0 | U13: =+R13+T13 -> 0
C15: Feeder Wires and Conduit | P15: =SUM(P9:P14) -> 4.02 | R15: =SUM(R9:R14) -> 715.56 | T15: =SUM(T9:T14) -> 0 | U15: =SUM(U9:U14) -> 715.56
B16: A.1 | C16: Feeders Total | P16: =P15 -> 4.02 | R16: =R15 -> 715.56 | T16: =T15 -> 0 | U16: =U15 -> 715.56
B18: A.3 | C18: Power Supply for Lighting and Small Power
C19: Wiring Devices (Power Receptacles, Etc. includes boxes)
C20: ='TAKEOFF DETAIL'!B26 -> Junction Box | E20: X | F20: X | I20: ='TAKEOFF DETAIL'!BH26+'TAKEOFF DETAIL'!L61 -> 263 | K20: ='TAKEOFF DETAIL'!BR26 -> 0 | N20: =I20+K20 -> 263 | P20: =IF(N20>0,N20*Q20,O20*Q20) -> 131.5 | Q20: 0.5 | R20: =P20*$N$2 -> 23407 | T20: =(N20+O20)*S20 -> 0 | U20: =+R20+T20 -> 23407 | V20: NECA
C21: ='TAKEOFF DETAIL'!B27 -> Junction Box, Weatherproof | E21: X | F21: X | I21: ='TAKEOFF DETAIL'!BH27 -> 0 | K21: ='TAKEOFF DETAIL'!BR27 -> 10 | N21: =I21+K21 -> 10 | P21: =IF(N21>0,N21*Q21,O21*Q21) -> 5 | Q21: 0.5 | R21: =P21*$N$2 -> 890 | T21: =(N21+O21)*S21 -> 0 | U21: =+R21+T21 -> 890 | V21: NECA
C22: ='TAKEOFF DETAIL'!B28 -> Duplex Receptacle | E22: X | F22: X | I22: ='TAKEOFF DETAIL'!BH28 -> 32 | K22: ='TAKEOFF DETAIL'!BR28 -> 0 | N22: =I22+K22 -> 32 | P22: =IF(N22>0,N22*Q22,O22*Q22) -> 12.8 | Q22: 0.4 | R22: =P22*$N$2 -> 2278.4 | T22: =(N22+O22)*S22 -> 0 | U22: =+R22+T22 -> 2278.4 | V22: NECA
C23: ='TAKEOFF DETAIL'!B29 -> Duplex Dedicated Receptacle | E23: X | F23: X | I23: ='TAKEOFF DETAIL'!BH29 -> 7 | K23: ='TAKEOFF DETAIL'!BR29 -> 0 | N23: =I23+K23 -> 7 | P23: =IF(N23>0,N23*Q23,O23*Q23) -> 2.8 | Q23: 0.4 | R23: =P23*$N$2 -> 498.4 | T23: =(N23+O23)*S23 -> 0 | U23: =+R23+T23 -> 498.4 | V23: NECA
C24: ='TAKEOFF DETAIL'!B30 -> Duplex Receptacle, with Surge Protection Device | E24: X | F24: X | I24: ='TAKEOFF DETAIL'!BH30 -> 2 | K24: ='TAKEOFF DETAIL'!BR30 -> 0 | N24: =I24+K24 -> 2 | P24: =IF(N24>0,N24*Q24,O24*Q24) -> 0.9 | Q24: 0.45 | R24: =P24*$N$2 -> 160.2 | T24: =(N24+O24)*S24 -> 0 | U24: =+R24+T24 -> 160.2 | V24: NECA
C25: =+'TAKEOFF DETAIL'!B65 -> Duplex Receptacle, GFCI Type WP | E25: X | F25: X | I25: =+'TAKEOFF DETAIL'!L65 -> 2 | K25: ='TAKEOFF DETAIL'!BR30 -> 0 | N25: =I25+K25 -> 2 | P25: =IF(N25>0,N25*Q25,O25*Q25) -> 0.9 | Q25: 0.45 | R25: =P25*$N$2 -> 160.2 | T25: =(N25+O25)*S25 -> 0 | U25: =+R25+T25 -> 160.2 | V25: NECA
C26: ='TAKEOFF DETAIL'!B31 -> Duplex Receptacle, Floor Mounted | E26: X | F26: X | I26: ='TAKEOFF DETAIL'!BH31 -> 4 | K26: ='TAKEOFF DETAIL'!BR31 -> 0 | N26: =I26+K26 -> 4 | P26: =IF(N26>0,N26*Q26,O26*Q26) -> 4 | Q26: 1 | R26: =P26*$N$2 -> 712 | T26: =(N26+O26)*S26 -> 0 | U26: =+R26+T26 -> 712 | V26: NECA
C27: ='TAKEOFF DETAIL'!B32 -> Quadruplex Receptacle | E27: X | F27: X | I27: ='TAKEOFF DETAIL'!BH32 -> 10 | K27: ='TAKEOFF DETAIL'!BR32 -> 0 | N27: =I27+K27 -> 10 | P27: =IF(N27>0,N27*Q27,O27*Q27) -> 8 | Q27: 0.8 | R27: =P27*$N$2 -> 1424 | T27: =(N27+O27)*S27 -> 0 | U27: =+R27+T27 -> 1424 | V27: NECA
C28: ='TAKEOFF DETAIL'!B33 -> Special Purpose Receptacle, NEMA 6-50R | E28: X | F28: X | I28: ='TAKEOFF DETAIL'!BH33 -> 2 | K28: ='TAKEOFF DETAIL'!BR33 -> 0 | N28: =I28+K28 -> 2 | P28: =IF(N28>0,N28*Q28,O28*Q28) -> 2 | Q28: 1 | R28: =P28*$N$2 -> 356 | T28: =(N28+O28)*S28 -> 0 | U28: =+R28+T28 -> 356 | V28: NECA | W28: https://www.mscdirect.com/product/details/48670590
C29: ='TAKEOFF DETAIL'!B34 -> Special Purpose Receptacle, NEMA 5-15R | E29: X | F29: X | I29: ='TAKEOFF DETAIL'!BH34 -> 2 | K29: ='TAKEOFF DETAIL'!BR34 -> 0 | N29: =I29+K29 -> 2 | P29: =IF(N29>0,N29*Q29,O29*Q29) -> 2 | Q29: 1 | R29: =P29*$N$2 -> 356 | T29: =(N29+O29)*S29 -> 0 | U29: =+R29+T29 -> 356 | V29: NECA
C30: ='TAKEOFF DETAIL'!B35 -> Special Purpose Receptacle, NEMA 14-50R | E30: X | F30: X | I30: ='TAKEOFF DETAIL'!BH35 -> 2 | K30: ='TAKEOFF DETAIL'!BR35 -> 0 | N30: =I30+K30 -> 2 | P30: =IF(N30>0,N30*Q30,O30*Q30) -> 2 | Q30: 1 | R30: =P30*$N$2 -> 356 | T30: =(N30+O30)*S30 -> 0 | U30: =+R30+T30 -> 356 | V30: NECA | W30: https://www.mscdirect.com/product/details/48670665
C31: ='TAKEOFF DETAIL'!B36 -> Special Purpose Receptacle, NEMA 6-30R | E31: X | F31: X | I31: ='TAKEOFF DETAIL'!BH36 -> 2 | K31: ='TAKEOFF DETAIL'!BR36 -> 0 | N31: =I31+K31 -> 2 | P31: =IF(N31>0,N31*Q31,O31*Q31) -> 2 | Q31: 1 | R31: =P31*$N$2 -> 356 | T31: =(N31+O31)*S31 -> 0 | U31: =+R31+T31 -> 356 | V31: NECA | W31: https://www.mscdirect.com/product/details/60512597
C32: ='TAKEOFF DETAIL'!B37 -> LeGrand Plugmold (MODEL#: BK20GB509TRUAC) | E32: X | F32: X | I32: ='TAKEOFF DETAIL'!BH37 -> 3 | K32: ='TAKEOFF DETAIL'!BR37 -> 0 | N32: =I32+K32 -> 3 | P32: =IF(N32>0,N32*Q32,O32*Q32) -> 6 | Q32: 2 | R32: =P32*$N$2 -> 1068 | T32: =(N32+O32)*S32 -> 0 | U32: =+R32+T32 -> 1068 | V32: NECA | W32: https://www.fergusonhome.com/legrand-20gb509truac/s2057263?srsltid=AfmBOoqJXTpd5-ZjDsxTNyuVEugW0DsiyVGCqS0ikTJyKgVWGh5bQuUW
C34: Wiring Devices (Power Receptacles, Etc. includes boxes) | P34: =SUM(P19:P33) -> 179.9 | R34: =SUM(R19:R33) -> 32022.2 | T34: =SUM(T19:T33) -> 0 | U34: =SUM(U19:U33) -> 32022.2
C35: Conduit and Wires (For Lighting and Small Power)
C36: =+'TAKEOFF DETAIL'!B11 -> 1/2" EMT Conduit | E36: X | F36: X | J36: ='TAKEOFF DETAIL'!BH11+'TAKEOFF DETAIL'!L57 -> 4540 | L36: ='TAKEOFF DETAIL'!BR11 -> 290 | O36: =J36+L36 -> 4830 | P36: =IF(N36>0,N36*Q36,O36*Q36) -> 217.35 | Q36: 0.045 | R36: =P36*$N$2 -> 38688.3 | S36: 0.424 | T36: =(N36+O36)*S36 -> 2047.92 | U36: =+R36+T36 -> 40736.22 | V36: NECA
C37: =+'TAKEOFF DETAIL'!B12 -> 3/4" EMT Conduit | E37: X | F37: X | J37: ='TAKEOFF DETAIL'!BH12 -> 350 | L37: ='TAKEOFF DETAIL'!BR12 -> 110 | O37: =J37+L37 -> 460 | P37: =IF(N37>0,N37*Q37,O37*Q37) -> 23 | Q37: 0.05 | R37: =P37*$N$2 -> 4094 | S37: 0.7509 | T37: =(N37+O37)*S37 -> 345.414 | U37: =+R37+T37 -> 4439.414 | V37: NECA
C38: =+'TAKEOFF DETAIL'!B13 -> 1" EMT Conduit | E38: X | F38: X | J38: ='TAKEOFF DETAIL'!BH13 -> 0 | L38: ='TAKEOFF DETAIL'!BR13 -> 60 | O38: =J38+L38 -> 60 | P38: =IF(N38>0,N38*Q38,O38*Q38) -> 3.3 | Q38: 0.055 | R38: =P38*$N$2 -> 587.4 | S38: 1.272 | T38: =(N38+O38)*S38 -> 76.32 | U38: =+R38+T38 -> 663.72 | V38: NECA
C39: ='TAKEOFF DETAIL'!B16 -> Copper Wire, 2#12 AWG + 1#12G AWG | E39: X | F39: X | J39: ='TAKEOFF DETAIL'!BH16+'TAKEOFF DETAIL'!L59 -> 6090 | L39: ='TAKEOFF DETAIL'!BR16 -> 290 | O39: =J39+L39 -> 6380 | P39: =IF(N39>0,N39*Q39,O39*Q39) -> 114.84 | Q39: =0.006*3 -> 0.018 | R39: =P39*$N$2 -> 20441.52 | S39: =0.18628*3 -> 0.55884 | T39: =(N39+O39)*S39 -> 3565.3992 | U39: =+R39+T39 -> 24006.919 | V39: NECA
C40: ='TAKEOFF DETAIL'!B17 -> Copper Wire, 2#10 AWG + 1#10G AWG | E40: X | F40: X | J40: ='TAKEOFF DETAIL'!BH17 -> 220 | L40: ='TAKEOFF DETAIL'!BR17 -> 0 | O40: =J40+L40 -> 220 | P40: =IF(N40>0,N40*Q40,O40*Q40) -> 4.62 | Q40: =0.007*3 -> 0.021 | R40: =P40*$N$2 -> 822.36 | S40: =0.28491*3 -> 0.85473 | T40: =(N40+O40)*S40 -> 188.0406 | U40: =+R40+T40 -> 1010.4006 | V40: NECA
C41: ='TAKEOFF DETAIL'!B18 -> Copper Wire, 2#8 AWG + 1#10G AWG | E41: X | F41: X | J41: ='TAKEOFF DETAIL'!BH18 -> 20 | L41: ='TAKEOFF DETAIL'!BR18 -> 0 | O41: =J41+L41 -> 20 | P41: =IF(N41>0,N41*Q41,O41*Q41) -> 0.5 | Q41: =0.009*2+0.007*1 -> 0.025 | R41: =P41*$N$2 -> 89 | S41: =0.54097*2+0.28491*1 -> 1.36685 | T41: =(N41+O41)*S41 -> 27.337 | U41: =+R41+T41 -> 116.337 | V41: NECA
C42: ='TAKEOFF DETAIL'!B19 -> Copper Wire, 3#12 AWG + 1#12G AWG | E42: X | F42: X | J42: ='TAKEOFF DETAIL'!BH19 -> 70 | L42: ='TAKEOFF DETAIL'!BR19 -> 70 | O42: =J42+L42 -> 140 | P42: =IF(N42>0,N42*Q42,O42*Q42) -> 3.36 | Q42: =0.006*4 -> 0.024 | R42: =P42*$N$2 -> 598.08 | S42: =0.18628*4 -> 0.74512 | T42: =(N42+O42)*S42 -> 104.3168 | U42: =+R42+T42 -> 702.3968 | V42: NECA
C43: ='TAKEOFF DETAIL'!B20 -> Copper Wire, 3#10 AWG + 1#10G AWG | E43: X | F43: X | J43: ='TAKEOFF DETAIL'!BH20 -> 0 | L43: ='TAKEOFF DETAIL'!BR20 -> 50 | O43: =J43+L43 -> 50 | P43: =IF(N43>0,N43*Q43,O43*Q43) -> 1.4 | Q43: =0.007*4 -> 0.028 | R43: =P43*$N$2 -> 249.2 | S43: =0.28491*4 -> 1.13964 | T43: =(N43+O43)*S43 -> 56.982 | U43: =+R43+T43 -> 306.182 | V43: NECA
C44: ='TAKEOFF DETAIL'!B21 -> Copper Wire, 3#8 AWG + 1#10G AWG | E44: X | F44: X | J44: ='TAKEOFF DETAIL'!BH21 -> 130 | L44: ='TAKEOFF DETAIL'!BR21 -> 80 | O44: =J44+L44 -> 210 | P44: =IF(N44>0,N44*Q44,O44*Q44) -> 7.14 | Q44: =0.009*3+0.007*1 -> 0.034 | R44: =P44*$N$2 -> 1270.92 | S44: =0.54097*3+0.28491*1 -> 1.90782 | T44: =(N44+O44)*S44 -> 400.6422 | U44: =+R44+T44 -> 1671.5622 | V44: NECA
C45: ='TAKEOFF DETAIL'!B22 -> Copper Wire, 3#4 AWG + 1#10G AWG | E45: X | F45: X | J45: ='TAKEOFF DETAIL'!BH22 -> 0 | L45: ='TAKEOFF DETAIL'!BR22 -> 70 | O45: =J45+L45 -> 70 | P45: =IF(N45>0,N45*Q45,O45*Q45) -> 3.22 | Q45: =0.013*3+0.007*1 -> 0.046 | R45: =P45*$N$2 -> 573.16 | S45: =1.22781*3+0.28491*1 -> 3.96834 | T45: =(N45+O45)*S45 -> 277.7838 | U45: =+R45+T45 -> 850.9438 | V45: NECA
C46: Conduit Fittings, support and Wire connectors | E46: X | F46: X | I46: 1 | N46: =I46+K46 -> 1 | P46: =IF(N46>0,N46*Q46,O46*Q46) -> 0 | R46: =P46*$N$2 -> 0 | S46: =SUM(T35:T45)*30% -> 2127.0467 | T46: =(N46+O46)*S46 -> 2127.0467 | U46: =+R46+T46 -> 2127.0467
C48: Conduit and Wires (For Lighting and Small Power) | P48: =SUM(P35:P47) -> 378.73 | R48: =SUM(R35:R47) -> 67413.94 | T48: =SUM(T35:T47) -> 9217.2023 | U48: =SUM(U35:U47) -> 76631.142
C49: Power Supply for Lighting and Small Power Total | P49: =P48+P34 -> 558.63 | R49: =R48+R34 -> 99436.14 | T49: =T48+T34 -> 9217.2023 | U49: =U48+U34 -> 108653.34
B51: A.5 | C51: Low Voltage System
B52: 3 | C52: Conduit, Wires, Boxes, and Devices
C53: ='TAKEOFF DETAIL'!B100 -> 3/4" EMT Conduit | E53: X | F53: X | J53: ='TAKEOFF DETAIL'!E100 -> 180 | O53: =J53+L53 -> 180 | P53: =IF(N53>0,N53*Q53,O53*Q53) -> 9 | Q53: 0.05 | R53: =P53*$N$2 -> 1602 | S53: 0.7509 | T53: =(N53+O53)*S53 -> 135.162 | U53: =+R53+T53 -> 1737.162 | V53: NECA
C54: Conduit Fittings and Support | E54: X | F54: X | I54: 1 | N54: =I54+K54 -> 1 | P54: =IF(N54>0,N54*Q54,O54*Q54) -> 0 | R54: =P54*$N$2 -> 0 | S54: =SUM(T52:T53)*40% -> 54.0648 | T54: =(N54+O54)*S54 -> 54.0648 | U54: =+R54+T54 -> 54.0648
C55: ='TAKEOFF DETAIL'!B102 -> Single gang box with mudring | E55: X | F55: X | I55: ='TAKEOFF DETAIL'!E102 -> 18 | N55: =I55+K55 -> 18 | P55: =IF(N55>0,N55*Q55,O55*Q55) -> 9 | Q55: 0.5 | R55: =P55*$N$2 -> 1602 | S55: 2.72 | T55: =(N55+O55)*S55 -> 48.96 | U55: =+R55+T55 -> 1650.96 | V55: NECA | W55: https://www.ebay.com/itm/226549530809?_skw=metal+electrical+junction+box&itmmeta=01JVXRDW8S6A1GBJS5YHDZN1A2&hash=item34bf6780b9:g:9GMAAOSwUZtniYw4&itmprp=enc%3AAQAKAAABAFkggFvd1GGDu0w3yXCmi1fROv%2BanpVGQjrQrSpomIortIIFIs66dmyO0ZmiJAyOW2V0mBGWtA9F%2Fhcp4z9oxC9VtnupjwGVYI1SUM%2Fegq%2B7SpEIClT4M%2BjFaW2JbQhEu9nJBWoHs3IcCNJ323a5%2FOnNpEovt6ypfk%2FtE4dlbXv342OKyjtRz%2BG2AQVzXAv7zFqWDW7MSkr3LhssVvk8dkDFJy%2B%2B5Cd3CKrCyiRF65TXZITGP8QUMmPLcI5hf458hqojJPiigiBwE9oukqkFkBCO1dA0MiG4gylbi1K8gdk2kDyQGV5j3py4u4QSHKGbe83V8WzHNE0fHgZZ%2BaBttJQ%3D%7Ctkp%3ABk9SR8rEt7jfZQ
C57: Conduit, Wires, Boxes, and Devices | P57: =SUM(P52:P56) -> 18 | R57: =SUM(R52:R56) -> 3204 | T57: =SUM(T52:T56) -> 238.1868 | U57: =SUM(U52:U56) -> 3442.1868
C58: Low Voltage System Total | P58: =+P57 -> 18 | R58: =+R57 -> 3204 | T58: =+T57 -> 238.1868 | U58: =+U57 -> 3442.1868
B60: A.2 | C60: Lighting Fixtures, Controls and Panelboards/Switchgears
C61: Panelboards and Equipments
C62: ='TAKEOFF DETAIL'!B39 -> Panel " C ", 100A MLO, 120/208V, 3P, 4W, 10KAIC, Surface Mtd., in NEMA 1 Enclosure | E62: X | F62: X | I62: =+'TAKEOFF DETAIL'!BU39 -> 1 | N62: =I62+K62 -> 1 | P62: =IF(N62>0,N62*Q62,O62*Q62) -> 10 | Q62: 10 | R62: =P62*$N$2 -> 1780 | T62: =(N62+O62)*S62 -> 0 | U62: =+R62+T62 -> 1780 | V62: NECA | W62: https://www.se.com/us/en/product/VH321NRB/safety-switch-visipact-heavy-duty-fused-viewing-window-nema-3r-240v-30a-3-pole-neutral-installed/?range=7273-heavy-duty-safety-switches&selectedNodeId=12144223672
C63: ='TAKEOFF DETAIL'!B40 -> Branches:
C64: ='TAKEOFF DETAIL'!B41 -> 1 - 15A, 2P, Circuit Breaker
C65: ='TAKEOFF DETAIL'!B42 -> 18 - 20A, 1P, Circuit Breaker
C66: ='TAKEOFF DETAIL'!B43 -> 3 - 15A, 1P, Circuit Breaker
C67: ='TAKEOFF DETAIL'!B44 -> 19 - Space
C68: ='TAKEOFF DETAIL'!B45 -> Disconnect Switch, 80A, 3P, in NEMA 3R Enclosure | E68: X | F68: X | I68: ='TAKEOFF DETAIL'!BH45 -> 0 | K68: ='TAKEOFF DETAIL'!BR45 -> 1 | N68: =I68+K68 -> 1 | P68: =IF(N68>0,N68*Q68,O68*Q68) -> 3 | Q68: 3 | R68: =P68*$N$2 -> 534 | T68: =(N68+O68)*S68 -> 0 | U68: =+R68+T68 -> 534 | V68: NECA
C69: ='TAKEOFF DETAIL'!B46 -> Disconnect Switch, 50A, 3P, in NEMA 3R Enclosure | E69: X | F69: X | I69: ='TAKEOFF DETAIL'!BH46 -> 0 | K69: ='TAKEOFF DETAIL'!BR46 -> 1 | N69: =I69+K69 -> 1 | P69: =IF(N69>0,N69*Q69,O69*Q69) -> 2 | Q69: 2 | R69: =P69*$N$2 -> 356 | T69: =(N69+O69)*S69 -> 0 | U69: =+R69+T69 -> 356 | V69: NECA
C70: ='TAKEOFF DETAIL'!B47 -> Disconnect Switch, 30A, 3P, in NEMA 3R Enclosure | E70: X | F70: X | I70: ='TAKEOFF DETAIL'!BH47 -> 0 | K70: ='TAKEOFF DETAIL'!BR47 -> 1 | N70: =I70+K70 -> 1 | P70: =IF(N70>0,N70*Q70,O70*Q70) -> 2 | Q70: 2 | R70: =P70*$N$2 -> 356 | T70: =(N70+O70)*S70 -> 0 | U70: =+R70+T70 -> 356 | V70: NECA
C71: ='TAKEOFF DETAIL'!B48 -> Disconnect Switch, 30A, 2P, in NEMA 3R Enclosure | E71: X | F71: X | I71: ='TAKEOFF DETAIL'!BH48 -> 1 | K71: ='TAKEOFF DETAIL'!BR48 -> 0 | N71: =I71+K71 -> 1 | P71: =IF(N71>0,N71*Q71,O71*Q71) -> 2 | Q71: 2 | R71: =P71*$N$2 -> 356 | T71: =(N71+O71)*S71 -> 0 | U71: =+R71+T71 -> 356 | V71: NECA
C73: Panelboards and Equipments | P73: =SUM(P61:P72) -> 19 | R73: =SUM(R61:R72) -> 3382 | T73: =SUM(T61:T72) -> 0 | U73: =SUM(U61:U72) -> 3382
C74: Lighting Fixtures and Lighting Controls (Owner Supplied)
C75: ='TAKEOFF DETAIL'!B62 -> Wall Motion Sensor | E75: X | F75: X | I75: ='TAKEOFF DETAIL'!L62 -> 2 | N75: =I75+K75 -> 2 | P75: =IF(N75>0,N75*Q75,O75*Q75) -> 1 | Q75: 0.5 | R75: =P75*$N$2 -> 178 | S75: "Owner Supplied" | T75: 0 | U75: =+R75+T75 -> 178 | V75: NECA | W75: https://www.ebay.com/itm/305603188973?_skw=MOTION+SENSOR+SWITCH%2C+UNIT+SHALL+INCLUDE+MANUAL+ON%2FOFF+INTEGRAL+TO+SENSOR+UNIT%2C+WITH+POWERPACK%2C+WALL+MTD.&itmmeta=01K8YW5GAS09715MMX1DAX3MNB&hash=item47275e98ed:g:JsgAAOSwolZlgxfH&itmprp=enc%3AAQAKAAABMFkggFvd1GGDu0w3yXCmi1c5PrZH9o2u20BnqrU9Zf5XZrCI63qMGBPSJyTe6r6bV932YEy6qWMCLF7X3jU27rdS2Z0PTSOczeVVyC7zaD%2Buo2zWUYveS3bmLzNF07StqxxyEb3Q4PE2n5AxGw%2FLcecdzu3GePYb3o0f4SURXsjax22qPONEuTIQJqnpItYIO0o8jHznPmzLhuS%2FYY%2FjswN4%2B51vYmzCdQx%2Bmh7iDZOPze07Ow0R24kX1S7gNFE1ISoXJdyESBtGh3WqI5XuYZAJt4Amuo37tKc%2FLTClalQl75Jw73T%2FLuUhZE%2FfIBSZHFBV%2FyImtrDq7S%2BNisebZehtSn5tpkXhQygKf2Xrd9vDagRocDRNt8URazDiUG3AGqUKz6zTocxU2w4OSwHoCuE%3D%7Ctkp%3ABk9SR8CFltzHZg
C76: ='TAKEOFF DETAIL'!B63 -> Switchbank complete with 9-Dimmer Switch | E76: X | F76: X | I76: ='TAKEOFF DETAIL'!L63 -> 1 | N76: =I76+K76 -> 1 | P76: =IF(N76>0,N76*Q76,O76*Q76) -> 4.5 | Q76: =0.5*9 -> 4.5 | R76: =P76*$N$2 -> 801 | S76: "Owner Supplied" | T76: 0 | U76: =+R76+T76 -> 801 | V76: NECA | W76: https://www.ebay.com/itm/397021260933?_skw=DIMMER+SWITCH%2C+WALL+MTD.&itmmeta=01K8YWH0K0SXBWQ1CTCQZCPC2R&hash=item5c704fac85:g:ofcAAeSwRNJouG5I&itmprp=enc%3AAQAKAAAA8FkggFvd1GGDu0w3yXCmi1fFGGYh32G7yZ1Kym2GQPAooift9NOfoQp3iquGwcwakUANKT07oyYAwwkPlXfYrgWFbpZRShM877qhsdeWewyH4r91eSF2P1RDaT0WCRUQGLrX4NNn3PlI9B0XmnbNAfbcemf2hCbs6SP3jkEsvL%2BUTW18Vdh%2Fh%2FoslbaF%2B39n8dz%2FqgWPLCbowOgZh07bMDF8d1h2l%2BKNqV7VQVjpA6lQRQsY6ZPicScfaQvPRT4rRlrDGQJkTMShruMjsRA3eS1DhoWjyg604w3w4iKTBE1rTEl7Khu3cwEUniH51i86Dg%3D%3D%7Ctkp%3ABFBM0InE3Mdm
C77: ='TAKEOFF DETAIL'!B64 -> 24VDC Drive for LED Strip Light | E77: X | F77: X | I77: ='TAKEOFF DETAIL'!L64 -> 8 | N77: =I77+K77 -> 8 | P77: =IF(N77>0,N77*Q77,O77*Q77) -> 4 | Q77: 0.5 | R77: =P77*$N$2 -> 712 | S77: "Owner Supplied" | T77: 0 | U77: =+R77+T77 -> 712 | V77: NECA | W77: https://www.ebay.com/itm/355619900469?_skw=24VDC+DRIVER&itmmeta=01K8YWXFDNSDK07F1F0PKQG1YZ&hash=item52cc990c35:g:tqAAAOSwTP1mFWG3&itmprp=enc%3AAQAKAAAA4FkggFvd1GGDu0w3yXCmi1cb0p2QHLfe6FlkI6bSLk%2FuAULcA%2FMHiEX5Zpavn4o3XeIOfJ1in355Abbirc2tYnkd%2B7fNFOjLkGzy4%2BY62TbREb%2Flp0QKfqTjOAa7wv1ZP51gmeJOXD8l1YxovG3D9%2FFRkXpEVSLfkjq2j827S4ve8q5sixQXNp4GmOUnb26h1ilSluNhCaKQRxcSP4n8y7sQsFPbEQ12H2JUe9yoF2McJDNvH77g86J%2BlpfKC08lePYdGO5roqEsvzuug%2BxiTXi56LIQE24I4OgtMG95zOm9%7Ctkp%3ABFBMgvf13Mdm
C78: ='TAKEOFF DETAIL'!B67 -> Type " 19045 ", LED Exit Sign with Emergency Light | F78: X | G78: X | I78: ='TAKEOFF DETAIL'!L67 -> 1 | N78: =I78+K78 -> 1 | P78: =IF(N78>0,N78*Q78,O78*Q78) -> 1.5 | Q78: 1.5 | R78: =P78*$N$2 -> 267 | S78: "Owner Supplied" | T78: 0 | U78: =+R78+T78 -> 267 | V78: NECA
C79: ='TAKEOFF DETAIL'!B68 -> Type " 19047 ", LED Exit Sign with Emergency Light | F79: X | G79: X | I79: ='TAKEOFF DETAIL'!L68 -> 4 | N79: =I79+K79 -> 4 | P79: =IF(N79>0,N79*Q79,O79*Q79) -> 6 | Q79: 1.5 | R79: =P79*$N$2 -> 1068 | S79: "Owner Supplied" | T79: 0 | U79: =+R79+T79 -> 1068 | V79: NECA
C80: ='TAKEOFF DETAIL'!B69 -> Type " 19056 ", LED Emergency Light | F80: X | G80: X | I80: ='TAKEOFF DETAIL'!L69 -> 1 | N80: =I80+K80 -> 1 | P80: =IF(N80>0,N80*Q80,O80*Q80) -> 1.5 | Q80: 1.5 | R80: =P80*$N$2 -> 267 | S80: "Owner Supplied" | T80: 0 | U80: =+R80+T80 -> 267 | V80: NECA
C81: ='TAKEOFF DETAIL'!B70 -> Type " 21769 ", Recessed Can Light | F81: X | G81: X | I81: ='TAKEOFF DETAIL'!L70 -> 35 | N81: =I81+K81 -> 35 | P81: =IF(N81>0,N81*Q81,O81*Q81) -> 28 | Q81: 0.8 | R81: =P81*$N$2 -> 4984 | S81: "Owner Supplied" | T81: 0 | U81: =+R81+T81 -> 4984 | V81: NECA
C82: ='TAKEOFF DETAIL'!B71 -> Type " 21769 ", Recessed Can Light with Emergency Lighting Inverter | F82: X | G82: X | I82: ='TAKEOFF DETAIL'!L71 -> 2 | N82: =I82+K82 -> 2 | P82: =IF(N82>0,N82*Q82,O82*Q82) -> 1.6 | Q82: 0.8 | R82: =P82*$N$2 -> 284.8 | S82: "Owner Supplied" | T82: 0 | U82: =+R82+T82 -> 284.8 | V82: NECA
C83: ='TAKEOFF DETAIL'!B72 -> Type " 21771 ", Recessed Can Light | F83: X | G83: X | I83: ='TAKEOFF DETAIL'!L72 -> 20 | N83: =I83+K83 -> 20 | P83: =IF(N83>0,N83*Q83,O83*Q83) -> 16 | Q83: 0.8 | R83: =P83*$N$2 -> 2848 | S83: "Owner Supplied" | T83: 0 | U83: =+R83+T83 -> 2848 | V83: NECA
C84: ='TAKEOFF DETAIL'!B73 -> Type " 21772 ", Recessed Can Light | F84: X | G84: X | I84: ='TAKEOFF DETAIL'!L73 -> 11 | N84: =I84+K84 -> 11 | P84: =IF(N84>0,N84*Q84,O84*Q84) -> 8.8 | Q84: 0.8 | R84: =P84*$N$2 -> 1566.4 | S84: "Owner Supplied" | T84: 0 | U84: =+R84+T84 -> 1566.4 | V84: NECA
C85: ='TAKEOFF DETAIL'!B74 -> Type " 21772 ", Recessed Can Light with Emergency Lighting Inverter | F85: X | G85: X | I85: ='TAKEOFF DETAIL'!L74 -> 2 | N85: =I85+K85 -> 2 | P85: =IF(N85>0,N85*Q85,O85*Q85) -> 1.6 | Q85: 0.8 | R85: =P85*$N$2 -> 284.8 | S85: "Owner Supplied" | T85: 0 | U85: =+R85+T85 -> 284.8 | V85: NECA
C86: ='TAKEOFF DETAIL'!B75 -> Type " 20749 ", Wall Sconce | F86: X | G86: X | I86: ='TAKEOFF DETAIL'!L75 -> 1 | N86: =I86+K86 -> 1 | P86: =IF(N86>0,N86*Q86,O86*Q86) -> 1.25 | Q86: 1.25 | R86: =P86*$N$2 -> 222.5 | S86: "Owner Supplied" | T86: 0 | U86: =+R86+T86 -> 222.5 | V86: NECA
C87: ='TAKEOFF DETAIL'!B76 -> Type " 20750 ", Wall Sconce | F87: X | G87: X | I87: ='TAKEOFF DETAIL'!L76 -> 2 | N87: =I87+K87 -> 2 | P87: =IF(N87>0,N87*Q87,O87*Q87) -> 2.5 | Q87: 1.25 | R87: =P87*$N$2 -> 445 | S87: "Owner Supplied" | T87: 0 | U87: =+R87+T87 -> 445 | V87: NECA
C88: ='TAKEOFF DETAIL'!B77 -> Type " X0501 ", Wall Sconce | F88: X | G88: X | I88: ='TAKEOFF DETAIL'!L77 -> 2 | N88: =I88+K88 -> 2 | P88: =IF(N88>0,N88*Q88,O88*Q88) -> 2.5 | Q88: 1.25 | R88: =P88*$N$2 -> 445 | S88: "Owner Supplied" | T88: 0 | U88: =+R88+T88 -> 445 | V88: NECA
C89: ='TAKEOFF DETAIL'!B78 -> Type " 17796 ", LED String Light @ 10'-9'' | F89: X | G89: X | I89: ='TAKEOFF DETAIL'!L78 -> 7 | N89: =I89+K89 -> 7 | P89: =IF(N89>0,N89*Q89,O89*Q89) -> 11.2 | Q89: 1.6 | R89: =P89*$N$2 -> 1993.6 | S89: "Owner Supplied" | T89: 0 | U89: =+R89+T89 -> 1993.6 | V89: NECA
... C103: ='TAKEOFF DETAIL'!B92 -> Type " 21783 " - Recessed LED Trofer | F103: X | G103: X | I103: ='TAKEOFF DETAIL'!L92 -> 6 | N103: =I103+K103 -> 6 | P103: =IF(N103>0,N103*Q103,O103*Q103) -> 6 | Q103: 1 | R103: =P103*$N$2 -> 1068 | S103: "Owner Supplied" | T103: 0 | U103: =+R103+T103 -> 1068 | V103: NECA
C105: Lighting Fixtures and Lighting Controls | P105: =SUM(P74:P104) -> 197.9 | R105: =SUM(R74:R104) -> 35226.2 | T105: =SUM(T74:T104) -> 0 | U105: =SUM(U74:U104) -> 35226.2
C106: Lighting Fixtures, Controls and Panelboards/Switchgears | P106: =P73+P105 -> 216.9 | R106: =R73+R105 -> 38608.2 | T106: =T73+T105 -> 0 | U106: =U73+U105 -> 38608.2
C108: SUPPLY & INSTALLATION OR INSTALLATION ONLY OF LIGHTING FIXTURES, EQUIPMENT, WIRING DEVICES ETC. FOR POWER, LIGHTING AND LOW VOLTAGE | O108: TOTAL | P108: =P16+P49+P58+P106 -> 797.55 | R108: =R16+R49+R58+R106 -> 141963.9 | T108: =T16+T49+T58+T106 -> 9455.3891 | U108: =U16+U49+U58+U106 -> 151419.29
O125: `

Sheet BREAKDOWN (SITE)
C1: =+'BREAKDOWN (BUILDING)'!C1 -> Project Name: University Park Village (Starbucks 6212)
C2: =+'BREAKDOWN (BUILDING)'!C2 -> Address: 1620 S University Dr, Fort Worth, TX 76107 | M2: Labor Rate: | N2: 178 | O2: Per Hour | P2: Source: | Q2: NECA
C3: =+'BREAKDOWN (BUILDING)'!C3 -> Plan Date: 8/27/2025
B4: Electrical | C4: Electrical | I4: 1ST FLOOR | K4: 2ND FLOOR | N4: TOTAL | P4: Total Labor Hrs | Q4: Labor Hours | R4: Total Labor Cost | S4: Material Pricing | T4: Total Material Pricing | U4: Total | V4: REFERENCE
B5: Item No. | C5: Description | D5: Added Description | I5: Qty | J5: Lin. Ft. | K5: Qty | L5: Lin. Ft. | N5: Qty | O5: Lin. Ft. | V5: LABOR HOURS
C6: EXTERIOR ELECTRICAL WORKS | E6: CONTRACTOR | G6: CLIENT / VENDOR
E7: PROVIDE | F7: INSTALL | G7: PROVIDE | H7: INSTALL
B8: A.1 | C8: EXTERIOR ELECTRICAL WORKS (NOT IN SCOPE)
C9: Exterior Electrical Works
B12: A.1 | C12: EXTERIOR ELECTRICAL WORKS TOTAL | P12: =+P11 -> 0 | R12: =+R11 -> 0 | T12: =+T11 -> 0 | U12: =+U11 -> 0
O29: `

Sheet TAKEOFF DETAIL
B2: =+'BREAKDOWN (BUILDING)'!C1 -> Project Name: University Park Village (Starbucks 6212)
B3: =+'BREAKDOWN (BUILDING)'!C2 -> Address: 1620 S University Dr, Fort Worth, TX 76107
B4: =+'BREAKDOWN (BUILDING)'!C3 -> Plan Date: 8/27/2025
B6: DESCRIPTION OF WORK | C6: UNIT | D6: FIRST FLOOR | BH6: TOTAL (Power) | BI6: ROOF | BR6: TOTAL (Power) | BS6: FEEDER | BU6: TOTAL (Feeder) | BW6: DEVICE DROP | BX6: TERMINATION | BY6: PANELBOARD DROP | BZ6: SERVICE WIRE LOOP
D7: Panel: "A" | W7: Panel: "B" | AM7: Panel: "C" | AW7: Panel: "B" | BA7: Panel: "C" | BI7: Panel Name: PANEL " A " (EXISTING) - SHEET#: 003 | BM7: Panel Name: PANEL " A " (EXISTING) - SHEET#: 003 | BS7: Panel " C " (NEW) to Panel " A " (EXISTING) | BT7: --------
D8: Ckt #: 1 | E8: Ckt #: 3 | F8: Ckt #: 7,9 | G8: Ckt #: 11,13 | H8: Ckt #: 15 | I8: Ckt #: 19 | J8: Ckt #: 20 | K8: Ckt #: 21 | L8: Ckt #: 22 | M8: Ckt #: 23 | N8: Ckt #: 24,26 | O8: Ckt #: 25 | P8: Ckt #: 28,30 | Q8: Ckt #: 32 | R8: Ckt #: 34 | S8: Ckt #: 36 | T8: Ckt #: 38 | U8: Ckt #: 40 | V8: Ckt #: 42 | W8: Ckt #: 2 | X8: Ckt #: 4 | Y8: Ckt #: 5 | Z8: Ckt #: 7 | AA8: Ckt #: 8 | AB8: Ckt #: 9 | AC8: Ckt #: 10 | AD8: Ckt #: 11 | AE8: Ckt #: 12 | AF8: Ckt #: 14 | AG8: Ckt #: 16 | AH8: Ckt #: 18 | AI8: Ckt #: 20 | AJ8: Ckt #: 23,25 | AK8: Ckt #: 29,31 | AL8: Ckt #: 37,39 | AM8: Ckt #: 1 | AN8: Ckt #: 3 | AO8: Ckt #: 5 | AP8: Ckt #: 11 | AQ8: Ckt #: 13 | AR8: Ckt #: 14 | AS8: Ckt #: 15 | AT8: Ckt #: 16 | AU8: Ckt #: 18 | AV8: Ckt #: 25 | AW8: Ckt #: 27 | AX8: Ckt #: 34 | AY8: Ckt #: 36 | AZ8: Ckt #: 41 | BA8: Ckt #: 2 | BB8: Ckt #: 4 | BC8: Ckt #: 9 | BD8: Ckt #: 19 | BE8: Ckt #: 20 | BF8: Ckt #: 21 | BG8: Ckt #: 23 | BI8: Ckt #: 2,4,6 | BJ8: Ckt #: 8,10,12 | BK8: Ckt #: 14,16,18 | BL8: -------- | BM8: Ckt #: 6 | BN8: Ckt #: 8 | BO8: Ckt #: 10,12 | BP8: Ckt #: 17 | BQ8: --------
B9: POWER SYSTEM | D9: C.O. + Dis. Switch | E9: C.O. | F9: C.O. | G9: C.O. | H9: C.O. | I9: C.O. | J9: C.O. | K9: C.O. | L9: C.O. | M9: C.O. | N9: C.O. | O9: C.O. | P9: C.O. | Q9: C.O. | R9: C.O. | S9: C.O. | T9: C.O. | U9: C.O. | V9: C.O. | W9: C.O. | X9: C.O. | Y9: C.O. | Z9: C.O. | AA9: C.O. | AB9: C.O. | AC9: C.O. | AD9: C.O. | AE9: C.O. | AF9: C.O. | AG9: C.O. | AH9: C.O. | AI9: C.O. | AJ9: J-BOX | AK9: C.O. | AL9: C.O. | AM9: C.O. | AN9: C.O. | AO9: C.O. | AP9: C.O. | AQ9: C.O. | AR9: C.O. | AS9: C.O. | AT9: C.O. | AU9: C.O. | AV9: C.O. | AW9: C.O. | AX9: J-BOX | AY9: J-BOX | AZ9: C.O. | BA9: C.O. | BB9: J-BOX | BC9: C.O. | BD9: C.O. | BE9: J-BOX | BF9: C.O. | BG9: C.O. | BH9: FIRST FLOOR | BI9: Dis. Switch | BJ9: Dis. Switch | BK9: Dis. Switch | BM9: J-BOX | BN9: J-BOX | BO9: J-BOX | BP9: J-BOX | BR9: ROOF
B10: Conduit | BW10: 10 | BX10: 10 | BY10: 10 | BZ10: 0
B11: 1/2" EMT Conduit | C11: ft | E11: =20+SUM(E28:E48)*$BW$10+$BY$10 -> 40 | H11: =30+SUM(H28:H48)*$BW$10+$BY$10 -> 50 | I11: =30+SUM(I28:I48)*$BW$10+$BY$10 -> 50 | J11: =20+SUM(J28:J48)*$BW$10+$BY$10 -> 40 | K11: =20+SUM(K28:K48)*$BW$10+$BY$10 -> 40 | L11: =20+SUM(L28:L48)*$BW$10+$BY$10 -> 40 | M11: =20+SUM(M28:M48)*$BW$10+$BY$10 -> 40 | O11: =20+SUM(O28:O48)*$BW$10+$BY$10 -> 40 | Q11: =20+SUM(Q28:Q48)*$BW$10+$BY$10 -> 60 | R11: =30+SUM(R28:R48)*$BW$10+$BY$10 -> 50 | S11: =20+SUM(S28:S48)*$BW$10+$BY$10 -> 40 | T11: =20+SUM(T28:T48)*$BW$10+$BY$10 -> 50 | U11: =20+SUM(U28:U48)*$BW$10+$BY$10 -> 60 | V11: =10+40+SUM(V28:V48)*$BW$10+$BY$10 -> 70 | W11: =20+40+SUM(W28:W48)*$BW$10+$BY$10 -> 80 | X11: =20+40+SUM(X28:X48)*$BW$10+$BY$10 -> 80 | Y11: =10+40+SUM(Y28:Y48)*$BW$10+$BY$10 -> 70 | Z11: =10+40+SUM(Z28:Z48)*$BW$10+$BY$10 -> 70 | AA11: =20+40+SUM(AA28:AA48)*$BW$10+$BY$10 -> 80 | AB11: =10+40+SUM(AB28:AB48)*$BW$10+$BY$10 -> 70 | AC11: =20+40+SUM(AC28:AC48)*$BW$10+$BY$10 -> 80 | AD11: =30+40+SUM(AD28:AD48)*$BW$10+$BY$10 -> 90 | AE11: =10+40+SUM(AE28:AE48)*$BW$10+$BY$10 -> 70 | AF11: =10+40+SUM(AF28:AF48)*$BW$10+$BY$10 -> 70 | AG11: =40+SUM(AG28:AG48)*$BW$10+$BY$10 -> 60 | AH11: =40+SUM(AH28:AH48)*$BW$10+$BY$10 -> 60 | AI11: =50+SUM(AI28:AI48)*$BW$10+$BY$10 -> 70 | AJ11: =50+SUM(AJ28:AJ48)*$BW$10+$BY$10 -> 60 | AM11: =40+SUM(AM28:AM48)*$BW$10+$BY$10 -> 60 | AN11: =40+SUM(AN28:AN48)*$BW$10+$BY$10 -> 60 | AO11: =40+SUM(AO28:AO48)*$BW$10+$BY$10 -> 60 | AP11: =20+SUM(AP28:AP48)*$BW$10+$BY$10 -> 40 | AQ11: =40+SUM(AQ28:AQ48)*$BW$10+$BY$10 -> 70 | AR11: =20+40+SUM(AR28:AR48)*$BW$10+$BY$10 -> 80 | AS11: =40+SUM(AS28:AS48)*$BW$10+$BY$10 -> 60 | AT11: =20+40+SUM(AT28:AT48)*$BW$10+$BY$10 -> 80 | AU11: =20+40+SUM(AU28:AU48)*$BW$10+$BY$10 -> 80 | AV11: =20+SUM(AV28:AV48)*$BW$10+$BY$10 -> 40 | AW11: =80+SUM(AW28:AW48)*$BW$10+$BY$10 -> 110 | AX11: =60+SUM(AX28:AX48)*$BW$10+$BY$10 -> 70 | AY11: =70+SUM(AY28:AY48)*$BW$10+$BY$10 -> 80 | AZ11: =10+40+SUM(AZ28:AZ48)*$BW$10+$BY$10 -> 70 | BA11: =20+SUM(BA28:BA48)*$BW$10+$BY$10 -> 40 | BB11: =60+SUM(BB28:BB48)*$BW$10+$BY$10 -> 100 | BC11: =100+SUM(BC28:BC48)*$BW$10+$BY$10 -> 150 | BD11: =50+SUM(BD28:BD48)*$BW$10+$BY$10 -> 90 | BE11: =40+SUM(BE28:BE48)*$BW$10+$BY$10 -> 50 | BF11: =20+SUM(BF28:BF48)*$BW$10+$BY$10 -> 40 | BG11: =20+SUM(BG28:BG48)*$BW$10+$BY$10 -> 40 | BH11: =SUM(D11:BG11) -> 3150 | BM11: =70+10+SUM(BM28:BM48)*$BW$10+$BY$10 -> 90 | BN11: =50+10+SUM(BN28:BN48)*$BW$10+$BY$10 -> 70 | BO11: =40+10+SUM(BO28:BO48)*$BW$10+$BY$10 -> 60 | BP11: =50+10+SUM(BP28:BP48)*$BW$10+$BY$10 -> 70 | BR11: =SUM(BI11:BQ11) -> 290 | BU11: =SUM(BS11:BT11) -> 0
B12: 3/4" EMT Conduit | C12: ft | D12: =20+10+SUM(D28:D48)*$BW$10+$BY$10 -> 60 | F12: =40+SUM(F28:F48)*$BW$10+$BY$10 -> 60 | G12: =40+SUM(G28:G48)*$BW$10+$BY$10 -> 60 | N12: =30+SUM(N28:N48)*$BW$10+$BY$10 -> 50 | P12: =40+SUM(P28:P48)*$BW$10+$BY$10 -> 60 | AK12: =10+SUM(AK28:AK48)*$BW$10+$BY$10 -> 30 | AL12: =10+SUM(AL28:AL48)*$BW$10+$BY$10 -> 30 | BH12: =SUM(D12:BG12) -> 350 | BJ12: =40+10+SUM(BJ28:BJ48)*$BW$10+$BY$10 -> 70 | BK12: =10+10+SUM(BK28:BK48)*$BW$10+$BY$10 -> 40 | BR12: =SUM(BI12:BQ12) -> 110 | BU12: =SUM(BS12:BT12) -> 0
B13: 1" EMT Conduit | C13: ft | BH13: =SUM(D13:BG13) -> 0 | BI13: =30+10+SUM(BI28:BI48)*$BW$10+$BY$10 -> 60 | BR13: =SUM(BI13:BQ13) -> 60 | BU13: =SUM(BS13:BT13) -> 0
B14: 1-1/4" EMT Conduit | C14: ft | BH14: =SUM(D14:BG14) -> 0 | BR14: =SUM(BI14:BQ14) -> 0 | BS14: =10+$BY$10+$BY$10 -> 30 | BU14: =SUM(BS14:BT14) -> 30
B15: Wires
B16: Copper Wire, 2#12 AWG + 1#12G AWG | C16: ft | E16: =+(SUM(E28:E48)*$BX$10+$BZ$10*2+E11) -> 50 | H16: =+(SUM(H28:H48)*$BX$10+$BZ$10*2+H11) -> 60 | I16: =+(SUM(I28:I48)*$BX$10+$BZ$10*2+I11) -> 60 | J16: =+(SUM(J28:J48)*$BX$10+$BZ$10*2+J11) -> 50 | K16: =+(SUM(K28:K48)*$BX$10+$BZ$10*2+K11) -> 50 | L16: =+(SUM(L28:L48)*$BX$10+$BZ$10*2+L11) -> 50 | M16: =+(SUM(M28:M48)*$BX$10+$BZ$10*2+M11) -> 50 | O16: =+(SUM(O28:O48)*$BX$10+$BZ$10*2+O11) -> 50 | Q16: =+(SUM(Q28:Q48)*$BX$10+$BZ$10*2+Q11) -> 90 | R16: =+(SUM(R28:R48)*$BX$10+$BZ$10*2+R11) -> 60 | S16: =+(SUM(S28:S48)*$BX$10+$BZ$10*2+S11) -> 50 | T16: =+(SUM(T28:T48)*$BX$10+$BZ$10*2+T11) -> 70 | U16: =+(SUM(U28:U48)*$BX$10+$BZ$10*2+U11) -> 90 | V16: =+(SUM(V28:V48)*$BX$10+$BZ$10*2+V11) -> 80 | W16: =+(SUM(W28:W48)*$BX$10+$BZ$10*2+W11) -> 90 | X16: =+(SUM(X28:X48)*$BX$10+$BZ$10*2+X11) -> 90 | ... AI16: =+(SUM(AI28:AI48)*$BX$10+$BZ$10*2+AI11) -> 80 | AM16: =+(SUM(AM28:AM48)*$BX$10+$BZ$10*2+AM11) -> 70 | AN16: =+(SUM(AN28:AN48)*$BX$10+$BZ$10*2+AN11) -> 70 | AO16: =+(SUM(AO28:AO48)*$BX$10+$BZ$10*2+AO11) -> 70 | AP16: =+(SUM(AP28:AP48)*$BX$10+$BZ$10*2+AP11) -> 50 | AQ16: =+(SUM(AQ28:AQ48)*$BX$10+$BZ$10*2+AQ11) -> 90 | AR16: =+(SUM(AR28:AR48)*$BX$10+$BZ$10*2+AR11) -> 90 | AS16: =+(SUM(AS28:AS48)*$BX$10+$BZ$10*2+AS11) -> 70 | AT16: =+(SUM(AT28:AT48)*$BX$10+$BZ$10*2+AT11) -> 90 | ... AW16: =+(SUM(AW28:AW48)*$BX$10+$BZ$10*2+AW11) -> 130 | AX16: =+(SUM(AX26)*$BX$10+$BZ$10*2+AX11) -> 80 | AY16: =+(SUM(AY26)*$BX$10+$BZ$10*2+AY11) -> 90 | AZ16: =+(SUM(AZ28:AZ48)*$BX$10+$BZ$10*2+AZ11) -> 80 | BA16: =+(SUM(BA28:BA48)*$BX$10+$BZ$10*2+BA11) -> 50 | BB16: =+(SUM(BB26)*$BX$10+$BZ$10*2+BB11) -> 110 | BC16: =+(SUM(BC28:BC48)*$BX$10+$BZ$10*2+BC11) -> 190 | BD16: =+(SUM(BD28:BD48)*$BX$10+$BZ$10*2+BD11) -> 120 | BE16: =+(SUM(BE26)*$BX$10+$BZ$10*2+BE11) -> 60 | BF16: =+(SUM(BF28:BF48)*$BX$10+$BZ$10*2+BF11) -> 50 | BG16: =+(SUM(BG28:BG48)*$BX$10+$BZ$10*2+BG11) -> 50 | BH16: =SUM(D16:BG16) -> 3690 | BM16: =+(SUM(BM27)*$BX$10+$BZ$10*2+BM11) -> 100 | BN16: =+(SUM(BN27)*$BX$10+$BZ$10*2+BN11) -> 80 | BP16: =+(SUM(BP27)*$BX$10+$BZ$10*2+BP11) -> 110 | BR16: =SUM(BI16:BQ16) -> 290 | BU16: =SUM(BS16:BT16) -> 0
B17: Copper Wire, 2#10 AWG + 1#10G AWG | C17: ft | D17: =+(SUM(D28:D48)*$BX$10+$BZ$10*2+D12) -> 80 | F17: =+(SUM(F28:F48)*$BX$10+$BZ$10*2+F12) -> 70 | G17: =+(SUM(G28:G48)*$BX$10+$BZ$10*2+G12) -> 70 | BH17: =SUM(D17:BG17) -> 220 | BR17: =SUM(BI17:BQ17) -> 0 | BU17: =SUM(BS17:BT17) -> 0
B18: Copper Wire, 2#8 AWG + 1#10G AWG | C18: ft | AK18: =+(SUM(AK28:AK48)*$BX$10+$BZ$10*2+AK11) -> 10 | AL18: =+(SUM(AL28:AL48)*$BX$10+$BZ$10*2+AL11) -> 10 | BH18: =SUM(D18:BG18) -> 20 | BR18: =SUM(BI18:BQ18) -> 0 | BU18: =SUM(BS18:BT18) -> 0
B19: Copper Wire, 3#12 AWG + 1#12G AWG | C19: ft | AJ19: =+(SUM(AJ26)*$BX$10+$BZ$10*2+AJ11) -> 70 | BH19: =SUM(D19:BG19) -> 70 | BO19: =+(SUM(BO27)*$BX$10+$BZ$10*2+BO11) -> 70 | BR19: =SUM(BI19:BQ19) -> 70 | BU19: =SUM(BS19:BT19) -> 0
B20: Copper Wire, 3#10 AWG + 1#10G AWG | C20: ft | BH20: =SUM(D20:BG20) -> 0 | BK20: =+(SUM(BK28:BK48)*$BX$10+$BZ$10*2+BK12) -> 50 | BR20: =SUM(BI20:BQ20) -> 50 | BU20: =SUM(BS20:BT20) -> 0
B21: Copper Wire, 3#8 AWG + 1#10G AWG | C21: ft | N21: =+(SUM(N28:N48)*$BX$10+$BZ$10*2+N12) -> 60 | P21: =+(SUM(P28:P48)*$BX$10+$BZ$10*2+P12) -> 70 | BH21: =SUM(D21:BG21) -> 130 | BJ21: =+(SUM(BJ28:BJ48)*$BX$10+$BZ$10*2+BJ12) -> 80 | BR21: =SUM(BI21:BQ21) -> 80 | BU21: =SUM(BS21:BT21) -> 0
B22: Copper Wire, 3#4 AWG + 1#10G AWG | C22: ft | BH22: =SUM(D22:BG22) -> 0 | BI22: =+(SUM(BI28:BI48)*$BX$10+$BZ$10*2+BI13) -> 70 | BR22: =SUM(BI22:BQ22) -> 70 | BU22: =SUM(BS22:BT22) -> 0
B23: Copper Wire, 1#3 AWG | C23: ft | BH23: =SUM(D23:BG23) -> 0 | BR23: =SUM(BI23:BQ23) -> 0 | BS23: =(BS14+$BX$10)*3 -> 120 | BU23: =SUM(BS23:BT23) -> 120
B24: Copper Wire, 1#8G AWG | C24: ft | BH24: =SUM(D24:BG24) -> 0 | BR24: =SUM(BI24:BQ24) -> 0 | BS24: =(BS14+$BX$10)*1 -> 40 | BU24: =SUM(BS24:BT24) -> 40
B25: Boxes and Wiring Devices
B26: Junction Box | C26: ea | D26: =SUM(D28:D47)*1+D32 -> 1 | E26: =SUM(E28:E47)*1+E32 -> 1 | F26: =SUM(F28:F47)*1+F32 -> 1 | G26: =SUM(G28:G47)*1+G32 -> 1 | H26: =SUM(H28:H47)*1+H32 -> 1 | I26: =SUM(I28:I47)*1+I32 -> 1 | J26: =SUM(J28:J47)*1+J32 -> 1 | K26: =SUM(K28:K47)*1+K32 -> 1 | ... T26: =SUM(T28:T47)*1+T32 -> 2 | U26: =SUM(U28:U47)*1+U32+1 -> 5 | V26: =SUM(V28:V47)*1+V32 -> 1 | W26: =SUM(W28:W47)*1+W32 -> 2 | X26: =SUM(X28:X47)*1+X32 -> 1 | Y26: =SUM(Y28:Y47)*1+Y32 -> 1 | Z26: =SUM(Z28:Z47)*1+Z32 -> 1 | AA26: =SUM(AA28:AA47)*1+AA32 -> 1 | AB26: =SUM(AB28:AB47)*1+AB32 -> 1 | AC26: =SUM(AC28:AC47)*1+AC32 -> 2 | ... AI26: =SUM(AI28:AI47)*1+AI32 -> 2 | AJ26: 1 | AK26: =SUM(AK28:AK47)*1+AK32 -> 1 | AL26: =SUM(AL28:AL47)*1+AL32 -> 1 | AM26: =SUM(AM28:AM47)*1+AM32 -> 2 | AN26: =SUM(AN28:AN47)*1+AN32 -> 1 | AO26: =SUM(AO28:AO47)*1+AO32 -> 1 | AP26: =SUM(AP28:AP47)*1+AP32 -> 1 | AQ26: =SUM(AQ28:AQ47)*1+AQ32 -> 3 | AR26: =SUM(AR28:AR47)*1+AR32 -> 1 | ... AW26: =SUM(AW28:AW47)*1+AW32 -> 2 | AX26: 1 | AY26: 1 | AZ26: =SUM(AZ28:AZ47)*1+AZ32 -> 1 | BA26: =SUM(BA28:BA47)*1+BA32 -> 1 | BB26: 1 | BC26: =SUM(BC28:BC47)*1+BC32 -> 4 | BD26: =SUM(BD28:BD47)*1+BD32 -> 3 | BE26: 1 | BF26: =SUM(BF28:BF47)*1+BF32 -> 1 | BG26: =SUM(BG28:BG47)*1+BG32 -> 1 | BH26: =SUM(D26:BG26) -> 79 | BR26: =SUM(BI26:BQ26) -> 0 | BU26: =SUM(BS26:BT26) -> 0
B27: Junction Box, Weatherproof | C27: ea | BH27: =SUM(D27:BG27) -> 0 | BI27: =SUM(BI28:BI47)*1+BI32 -> 1 | BJ27: =SUM(BJ28:BJ47)*1+BJ32 -> 1 | BK27: =SUM(BK28:BK47)*1+BK32 -> 1 | BM27: 1 | BN27: 1 | BO27: 1 | BP27: 4 | BR27: =SUM(BI27:BQ27) -> 10 | BU27: =SUM(BS27:BT27) -> 0
B28: Duplex Receptacle | C28: ea | I28: 1 | J28: 1 | K28: 1 | L28: 1 | Q28: 2 | S28: 1 | T28: 2 | U28: 2 | X28: 1 | Y28: 1 | Z28: 1 | AA28: 1 | AB28: 1 | AD28: 1 | AO28: 1 | AP28: 1 | AQ28: 1 | AS28: 1 | AU28: 1 | AV28: 1 | AW28: 2 | BC28: 4 | BD28: 3 | BH28: =SUM(D28:BG28) -> 32 | BR28: =SUM(BI28:BQ28) -> 0 | BU28: =SUM(BS28:BT28) -> 0
B29: Duplex Dedicated Receptacle | C29: ea | E29: 1 | H29: 1 | M29: 1 | O29: 1 | Q29: 1 | AN29: 1 | AR29: 1 | BH29: =SUM(D29:BG29) -> 7 | BR29: =SUM(BI29:BQ29) -> 0 | BU29: =SUM(BS29:BT29) -> 0
B30: Duplex Receptacle, with Surge Protection Device | C30: ea | AG30: 1 | AH30: 1 | BH30: =SUM(D30:BG30) -> 2 | BR30: =SUM(BI30:BQ30) -> 0 | BU30: =SUM(BS30:BT30) -> 0
B31: Duplex Receptacle, Floor Mounted | C31: ea | AZ31: 1 | BA31: 1 | BF31: 1 | BG31: 1 | BH31: =SUM(D31:BG31) -> 4 | BR31: =SUM(BI31:BQ31) -> 0 | BU31: =SUM(BS31:BT31) -> 0
B32: Quadruplex Receptacle | C32: ea | R32: 1 | U32: 1 | W32: 1 | AC32: 1 | AE32: 1 | AF32: 1 | AI32: 1 | AM32: 1 | AQ32: 1 | AT32: 1 | BH32: =SUM(D32:BG32) -> 10 | BR32: =SUM(BI32:BQ32) -> 0 | BU32: =SUM(BS32:BT32) -> 0
B33: Special Purpose Receptacle, NEMA 6-50R | C33: ea | AK33: 1 | AL33: 1 | BH33: =SUM(D33:BG33) -> 2 | BR33: =SUM(BI33:BQ33) -> 0 | BU33: =SUM(BS33:BT33) -> 0
B34: Special Purpose Receptacle, NEMA 5-15R | C34: ea | D34: 1 | V34: 1 | BH34: =SUM(D34:BG34) -> 2 | BR34: =SUM(BI34:BQ34) -> 0 | BU34: =SUM(BS34:BT34) -> 0
B35: Special Purpose Receptacle, NEMA 14-50R | C35: ea | N35: 1 | P35: 1 | BH35: =SUM(D35:BG35) -> 2 | BR35: =SUM(BI35:BQ35) -> 0 | BU35: =SUM(BS35:BT35) -> 0
B36: Special Purpose Receptacle, NEMA 6-30R | C36: ea | F36: 1 | G36: 1 | BH36: =SUM(D36:BG36) -> 2 | BR36: =SUM(BI36:BQ36) -> 0 | BU36: =SUM(BS36:BT36) -> 0
B37: LeGrand Plugmold (MODEL#: BK20GB509TRUAC) | C37: ea | BB37: 3 | BH37: =SUM(D37:BG37) -> 3 | BR37: =SUM(BI37:BQ37) -> 0 | BU37: =SUM(BS37:BT37) -> 0
B38: Boards and Equipments
B39: Panel " C ", 100A MLO, 120/208V, 3P, 4W, 10KAIC, Surface Mtd., in NEMA 1 Enclosure | C39: assy | BH39: =SUM(D39:BG39) -> 0 | BR39: =SUM(BI39:BQ39) -> 0 | BS39: 1 | BU39: =SUM(BS39:BT39) -> 1
B40: Branches:
B41: 1 - 15A, 2P, Circuit Breaker
B42: 18 - 20A, 1P, Circuit Breaker
B43: 3 - 15A, 1P, Circuit Breaker
B44: 19 - Space
B45: Disconnect Switch, 80A, 3P, in NEMA 3R Enclosure | C45: ea | BH45: =SUM(D45:BG45) -> 0 | BI45: 1 | BR45: =SUM(BI45:BQ45) -> 1 | BU45: =SUM(BS45:BT45) -> 0
B46: Disconnect Switch, 50A, 3P, in NEMA 3R Enclosure | C46: ea | BH46: =SUM(D46:BG46) -> 0 | BJ46: 1 | BR46: =SUM(BI46:BQ46) -> 1 | BU46: =SUM(BS46:BT46) -> 0
B47: Disconnect Switch, 30A, 3P, in NEMA 3R Enclosure | C47: ea | BH47: =SUM(D47:BG47) -> 0 | BK47: 1 | BR47: =SUM(BI47:BQ47) -> 1 | BU47: =SUM(BS47:BT47) -> 0
B48: Disconnect Switch, 30A, 2P, in NEMA 3R Enclosure | C48: ea | D48: 1 | BH48: =SUM(D48:BG48) -> 1 | BR48: =SUM(BI48:BQ48) -> 0 | BU48: =SUM(BS48:BT48) -> 0
B52: DESCRIPTION OF WORK | C52: UNIT | D52: FIRST FLOOR | L52: TOTAL (Lighting) FIRST FLOOR | N52: DEVICE DROP | O52: TERMINATION | P52: PANELBOARD DROP | Q52: SERVICE WIRE LOOP
D53: Panel: "A" | E53: Panel: "B" | K53: Panel: "C"
D54: Ckt #: 29 | E54: Ckt #: 13 | F54: Ckt #: 15 | G54: Ckt #: 17 | H54: Ckt #: 38 | I54: Ckt #: 40 | J54: Ckt #: 42 | K54: Ckt #: 7
B55: LIGHTING SYSTEM
B56: Conduit | N56: 10 | O56: 10 | P56: 10 | Q56: 0
B57: 1/2" EMT Conduit | C57: ft | D57: =500+D62*$N$56+D63*$N$56*9+$P$56 -> 600 | E57: =80+E62*$N$56+E63*$N$56*9+$P$56 -> 110 | F57: =90+F62*$N$56+F63*$N$56*9+$P$56 -> 100 | G57: =100+G62*$N$56+G63*$N$56*9+$P$56 -> 110 | H57: =190+H62*$N$56+H63*$N$56*9+$P$56 -> 200 | I57: =90+I62*$N$56+I63*$N$56*9+$P$56 -> 100 | J57: =90+J62*$N$56+J63*$N$56*9+$P$56 -> 100 | K57: =60+K62*$N$56+K63*$N$56*9+$P$56 -> 70 | L57: =SUM(D57:K57) -> 1390
B58: Wires
B59: Copper Wire, 2#12 AWG + 1#12G AWG | C59: ft | D59: =+((SUM(D62:D76)-D63)*$O$56+D63*$O$56*9+$Q$56*2+D57) -> 860 | E59: =+((SUM(E62:E76)-E63)*$O$56+E63*$O$56*9+$Q$56*2+E57) -> 200 | F59: =+((SUM(F62:F76)-F63)*$O$56+F63*$O$56*9+$Q$56*2+F57) -> 180 | G59: =+((SUM(G62:G76)-G63)*$O$56+G63*$O$56*9+$Q$56*2+G57) -> 480 | H59: =+((SUM(H62:H76)-H63)*$O$56+H63*$O$56*9+$Q$56*2+H57) -> 380 | I59: =+((SUM(I62:I76)-I63)*$O$56+I63*$O$56*9+$Q$56*2+I57) -> 110 | J59: =+((SUM(J62:J76)-J63)*$O$56+J63*$O$56*9+$Q$56*2+J57) -> 110 | K59: =+(K61*$O$56+$Q$56*2+K57) -> 80 | L59: =SUM(D59:K59) -> 2400
B60: Boxes and Wiring Devices
B61: Junction Box | C61: ea | D61: =SUM(D62:D92)-D63+D63*9 -> 87 | E61: =SUM(E62:E92)-E63+E63*9 -> 9 | F61: =SUM(F62:F92)-F63+F63*9 -> 15 | G61: =SUM(G62:G92)-G63+G63*9 -> 37 | H61: =SUM(H62:H92)-H63+H63*9 -> 24 | I61: =SUM(I62:I92)-I63+I63*9 -> 6 | J61: =SUM(J62:J92)-J63+J63*9 -> 5 | K61: 1 | L61: =SUM(D61:K61) -> 184
B62: Wall Motion Sensor | C62: ea | E62: 2 | L62: =SUM(D62:K62) -> 2
B63: Switchbank complete with 9-Dimmer Switch | C63: ea | D63: 1 | L63: =SUM(D63:K63) -> 1
B64: 24VDC Drive for LED Strip Light | C64: ea | F64: 8 | L64: =SUM(D64:K64) -> 8
B65: Duplex Receptacle, GFCI Type WP | C65: ea | I65: 1 | J65: 1 | L65: =SUM(D65:K65) -> 2
B66: Lighting Fixtures
B67: Type " 19045 ", LED Exit Sign with Emergency Light | C67: ea | H67: 1 | L67: =SUM(D67:K67) -> 1
B68: Type " 19047 ", LED Exit Sign with Emergency Light | C68: ea | E68: 1 | H68: 3 | L68: =SUM(D68:K68) -> 4
B69: Type " 19056 ", LED Emergency Light | C69: ea | H69: 1 | L69: =SUM(D69:K69) -> 1
B70: Type " 21769 ", Recessed Can Light | C70: ea | G70: 35 | L70: =SUM(D70:K70) -> 35
B71: Type " 21769 ", Recessed Can Light with Emergency Lighting Inverter | C71: ea | G71: 2 | L71: =SUM(D71:K71) -> 2
B72: Type " 21771 ", Recessed Can Light | C72: ea | D72: 16 | H72: 4 | L72: =SUM(D72:K72) -> 20
B73: Type " 21772 ", Recessed Can Light | C73: ea | E73: 2 | H73: 9 | L73: =SUM(D73:K73) -> 11
B74: Type " 21772 ", Recessed Can Light with Emergency Lighting Inverter | C74: ea | E74: 2 | L74: =SUM(D74:K74) -> 2
B75: Type " 20749 ", Wall Sconce | C75: ea | D75: 1 | L75: =SUM(D75:K75) -> 1
B76: Type " 20750 ", Wall Sconce | C76: ea | E76: 2 | L76: =SUM(D76:K76) -> 2
B77: Type " X0501 ", Wall Sconce | C77: ea | D77: 2 | L77: =SUM(D77:K77) -> 2
B78: Type " 17796 ", LED String Light @ 10'-9'' | C78: ea | I78: 4 | J78: 3 | L78: =SUM(D78:K78) -> 7
B79: Type " 17796 ", LED String Light @ 16'-6'' | C79: ea | I79: 1 | J79: 1 | L79: =SUM(D79:K79) -> 2
B80: Type " 21781 ", LED Tape Grazer @ 4' | C80: ea | F80: 2 | L80: =SUM(D80:K80) -> 2
B81: Type " 21781 ", LED Tape Grazer @ 6'-6" | C81: ea | F81: 1 | L81: =SUM(D81:K81) -> 1
B82: Type " 21781 ", LED Tape Grazer @ 12'-6" | C82: ea | F82: 1 | L82: =SUM(D82:K82) -> 1
B83: Type " 21782 ", LED Tape Light @ 12'-6" | C83: ea | F83: 1 | L83: =SUM(D83:K83) -> 1
B84: Type " 22217 ", LED Tape Flexible @ 6'-6" | C84: ea | F84: 1 | L84: =SUM(D84:K84) -> 1
B85: Type " 22217 ", LED Tape Flexible @ 13'-9" | C85: ea | F85: 1 | L85: =SUM(D85:K85) -> 1
B86: Type " 12947 ", 8' LED Track with connectors | C86: ea | D86: 17 | L86: =SUM(D86:K86) -> 17
B87: Type " 21777 ", LED Fixture with Snoot | C87: ea | D87: 11 | L87: =SUM(D87:K87) -> 11
B88: Type " 21779 ", LED Fixture with Snoot | C88: ea | D88: 28 | L88: =SUM(D88:K88) -> 28
B89: Type " X1060 ", 0.5A Current Limiter | C89: ea | D89: 1 | L89: =SUM(D89:K89) -> 1
B90: Type " X1120 ", 1A Current Limiter | C90: ea | D90: 1 | L90: =SUM(D90:K90) -> 1
B91: Type " X1240 ", 2A Current Limiter | C91: ea | D91: 1 | L91: =SUM(D91:K91) -> 1
B92: Type " 21783 " - Recessed LED Trofer | C92: ea | H92: 6 | L92: =SUM(D92:K92) -> 6
B95: DESCRIPTION OF WORK | C95: UNIT | D95: FIRST FLOOR | E95: TOTAL (LOW VOLTAGE) | G95: DEVICE DROP | H95: TERMINATION | I95: BOARD DROP | J95: SERVICE WIRE LOOP
B98: LOW VOLTAGE SYSTEM
B99: Conduit and Wires | G99: 10 | H99: 10 | I99: 10 | J99: 0
B100: 3/4" EMT Conduit | C100: ft | D100: =D102*10 -> 180 | E100: =SUM(D100:D100) -> 180
B101: Boxes and Devices
B102: Single gang box with mudring | C102: ea | D102: =SUM(D103:D109) -> 18 | E102: =SUM(D102:D102) -> 18
B103: SPEAKER GRILLE RECESSED - BLACK | C103: ea | D103: 5 | E103: =SUM(D103:D103) -> 5
B104: SPEAKER PENDANT MOUNTED - BLACK | C104: ea | D104: 3 | E104: =SUM(D104:D104) -> 3
B105: DIGITAL TEMPERATURE SENSOR | C105: ea | D105: 4 | E105: =SUM(D105:D105) -> 4
B106: MENU BOARD- DIGITAL MENU BOARD | C106: ea | D106: 1 | E106: =SUM(D106:D106) -> 1
B107: MENU BOARD- DIGITAL MENU DISPLAY | C107: ea | D107: 3 | E107: =SUM(D107:D107) -> 3
B108: AMPLIFIER- 60W | C108: ea | D108: 1 | E108: =SUM(D108:D108) -> 1
B109: MUSIC SYSTEM | C109: ea | D109: 1 | E109: =SUM(D109:D109) -> 1
