Workbook
Name adsf: #REF!
Name BID_FORM: #REF!
Name Build: #REF!
Name DBSUM: #REF!
Name FIRST_: #REF!
Name LOOPSUM: #REF!
Name Print_Area_MI: #REF!
Name qweqwe: #REF!
Name RECOMPARE: #REF!
Name RESTART: #REF!
Name SBINS: #REF!
Name SBRID: #REF!
Name SCONT: #REF!
Name SECOND_: #REF!
Name SELEC: #REF!
Name SEQUP: #REF!
Name SEXCV: #REF!
Name SEXCVA: #REF!
Name SEXCVB: #REF!
Name SEXTW: #REF!
Name sf: #REF!
Name SFARM: #REF!
Name SFEE_: #REF!
Name SFINS: #REF!
Name SFLOO: #REF!
Name SFPRT: #REF!
Name SGENC: #REF!
Name SHVAC: #REF!
Name SPERM: #REF!
Name SPLBG: #REF!
Name SRFWP: #REF!
Name SRFWPA: #REF!
Name SRFWPB: #REF!
Name SSCON: #REF!
Name SSERV: #REF!
Name SSITE: #REF!
Name SSPEC: #REF!
Name SSTRU: #REF!
Name SSTRUA: #REF!
Name SSTRUB: #REF!
Name SubcontractorTable: 'Item Breakdown'!$B$2886:$C$2939
Name SubcontractorTable: #REF!
Name SUMMARY: #REF!
Name SVERT: #REF!
Name SYSBORDER: #REF!
Name SYSTEMSPRINT: #REF!
Name TOTALSUM: #REF!
Name TRADEBORDER: #REF!
Name TRADEPRINT: #REF!
Name Unit: #REF!
Name UnitTypes: #REF!

Sheet NOTES
B1: NOTES
B3: Project Name : Starbucks #6212, University Park Village
B4: Location : 1620 S University Dr, Fort Worth, TX 76107
B5: Date of Drawings : Permit Set 8/28/2025
B7: DEMOLITION
B8: "Items to be preserved" list for items that shall be salvaged for relocation
B9: At locations where existing walls are to be removed existing walls to remain. Perform demolition without disturbing exisitng elements to remain
B10: Field verify type of construction and height of walls, Fields verify that walls to be removed do not provide support for existing building elements and existing construction to remain
B11: MEPs demolition are not included.
B12: Height of cubbies and menu board are assumed base on starbucks standard (https://www.navymwr.org/modules/media/?do=download&id=e4a72850-fe08-4e91-a9ce-0a7fa6f77cbe)
B13: Removal shall include any residual material after demolition i.e pieces of wall covering or backing. Removal of all coverings is to be done w/o damaging the existing wall surface to remain
B14: The manhours computed in the sheet include hauling, as well as the disassembly of any connections, fasteners, and accessories related to the item.
... B19: Exterior Siding
B20: ='Exterior Siding'!B7 -> Only Patching and repair area were considered in takeoffs.
B21: ='Exterior Siding'!B8 -> Brick Veneer considered in the takeoffs as per plan.
B22: Exterior Painting
B23: ='Exterior Painting'!B22 -> Two coats of stain paint are considered for the Exterior Patio Railings.
B24: ='Exterior Painting'!B23 -> One coat of primer and two coats of paint are considered for the Exterior Patio Posts.
B25: As per Key Note 6 , Patio Railing will be restained wood SW3524.
B26: As per Key Note 6 , Patio Post will be repainted SW7048.
B27: Metal Framing
B28: Wall Type per print A101, Interior New Wall Schedule.
B29: Jamb, Header, Soffit and Bracing details per print I509.
B30: Drywall
B31: Wall Type per print A101, Wall Sheating Key for wall type.
B32: See print I201-I204 for height reference.
B33: See print I103 for ceiling sched/type reference.
B34: Consider 5/8" GWB Type X for all wall and GWB Clg, U.N.O.
B35: Flooring & Tile
B36: Finish Material Schedule per print I603.
... B79: Considere 2x10 FRT blocking per detail 2 | I504

Sheet SUMMARY
C3: MATERIAL BREAKDOWN
C4: =NOTES!B3 -> Project Name : Starbucks #6212, University Park Village | E4: Proposal for plans dated: | F4: 45897
C5: =NOTES!B4 -> Location : 1620 S University Dr, Fort Worth, TX 76107 | E5: Floor Level: | F5: 1
E6: Total Square Footage (Building): | F6: 2758
E7: Total Square Footage (Site): | F7: --
D9: WORK DESCRIPTION | E9: TOTAL MANHOURS | F9: TOTAL MATERIAL COST
D11: ='Item Breakdown'!C14 -> DEMOLITION | E11: =ROUNDUP(SUM('Item Breakdown'!G16:G62),0) -> 166 | F11: ='Item Breakdown'!J65 -> 0
D12: ='Item Breakdown'!C67 -> LANDSCAPING | E12: =ROUNDUP(SUM('Item Breakdown'!G68:G88),0) -> 6 | F12: ='Item Breakdown'!J91 -> 0
D13: ='Item Breakdown'!C93 -> EXTERIOR SIDING | E13: =ROUNDUP(SUM('Item Breakdown'!G94:G96),0) -> 8 | F13: ='Item Breakdown'!J99 -> 0
D14: ='Item Breakdown'!C101 -> EXTERIOR PAINTING | E14: =ROUNDUP(SUM('Item Breakdown'!G102:G106),0) -> 16 | F14: ='Item Breakdown'!J109 -> 0
D15: ='Item Breakdown'!C111 -> METAL STUD FRAMING | E15: =ROUNDUP(SUM('Item Breakdown'!G112:G179),0) -> 59 | F15: ='Item Breakdown'!J182 -> 0
D16: ='Item Breakdown'!C184 -> DRYWALL | E16: =ROUNDUP(SUM('Item Breakdown'!G185:G200),0) -> 124 | F16: ='Item Breakdown'!J203 -> 0
D17: ='Item Breakdown'!C205 -> FLOORING & TILE | E17: =ROUNDUP(SUM('Item Breakdown'!G206:G219),0) -> 149 | F17: ='Item Breakdown'!J222 -> 0
D18: ='Item Breakdown'!C224 -> INTERIOR FINISHES | E18: =ROUNDUP(SUM('Item Breakdown'!G225:G239),0) -> 461 | F18: ='Item Breakdown'!J242 -> 0
D19: ='Item Breakdown'!C244 -> INTERIOR PAINTING | E19: =SUM('Item Breakdown'!G245:G273) -> 116 | F19: ='Item Breakdown'!J276 -> 0
D20: ='Item Breakdown'!C278 -> INTERIOR TRIM | E20: =ROUNDUP(SUM('Item Breakdown'!G279:G286),0) -> 3 | F20: ='Item Breakdown'!J289 -> 0
D21: ='Item Breakdown'!C291 -> OPENING | E21: =ROUNDUP(SUM('Item Breakdown'!G292:G318),0) -> 15 | F21: ='Item Breakdown'!J321 -> 0
D22: ='Item Breakdown'!C323 -> MILLWORK | E22: =ROUNDUP(SUM('Item Breakdown'!G324:G373),0) -> 58 | F22: ='Item Breakdown'!J376 -> 0
D23: ='Item Breakdown'!C378 -> SPECIALTIES | E23: =ROUNDUP(SUM('Item Breakdown'!G379:G452),0) -> 115 | F23: ='Item Breakdown'!J455 -> 0
D24: ='Item Breakdown'!C457 -> ROUGH CARPENTRY | E24: =ROUNDUP(SUM('Item Breakdown'!G458:G463),0) -> 18 | F24: ='Item Breakdown'!J466 -> 0
D26: TOTAL | E26: =SUM(E10:E24) -> 1314 | F26: =SUM(F10:F24) -> 0
C30: ALTERNATES
E31: TOTAL MANHOURS | F31: TOTAL MATERIAL COST
C32: 1
C33: 2

Sheet Item Breakdown
C3: =NOTES!B3 -> Project Name : Starbucks #6212, University Park Village
C4: =NOTES!B4 -> Location : 1620 S University Dr, Fort Worth, TX 76107
C5: =NOTES!B5 -> Date of Drawings : Permit Set 8/28/2025
G7: www.gclegacyconstruction.com
G8: 10455 Markison Rd., Dallas, TX 75238
C9: MATERIAL BREAKDOWN
C11: ITEM | D11: DESCRIPTION | E11: QTY | F11: UNIT | G11: MANHOURS | H11: CREW | I11: MATERIAL COST (Excluding Tax) | J11: Total | M11: Wastage | N11: Unit Material Cost
C14: DEMOLITION
C15: EXTERIOR
C16: DEMOLISH EXTERIOR FURNITURE | D16: This includes all tables and chairs | E16: 10 | F16: EA | G16: 3 | H16: MH, 2 WORKERS | I16: =E16*N16*(1+M16) -> 0 | J16: =SUM(I16) -> 0 | M16: 0 | N16: 0
C17: DEMOLISH EXISTING METAL AWNING | D17: GC to patch/repair wall as needed | E17: 260 | F17: SF | G17: 6.5 | H17: MH, 3 WORKERS | I17: =E17*N17*(1+M17) -> 0 | J17: =SUM(I17) -> 0 | M17: 0 | N17: 0
C18: DEMOLISH EXISTING METAL DECORATION OVER CLERESTORY WINDOWS | D18: 3'-4" Height as per sheet D103 | E18: 236.9 | F18: SF | G18: 6 | H18: MH, 3 WORKERS | I18: =E18*N18*(1+M18) -> 0 | J18: =SUM(I18) -> 0 | M18: 0 | N18: 0
C19: DEMOLISH EXISTING FABRIC COVERING ON PATIO STRUCTURE | D19: GC to prepare for new | E19: 184.5 | F19: SF | G19: 1.9 | H19: MH, 2 WORKERS | I19: =E19*N19*(1+M19) -> 0 | J19: =SUM(I19) -> 0 | M19: 0 | N19: 0
C21: INTERIOR
C22: DEMOLISH EXISTING WALL TO EXTENT SHOWN | D22: Average Height 10' (Ref D102 Sheet) | E22: 2082.8 | F22: SF | G22: 42 | H22: MH, 3 WORKERS | I22: =E22*N22*(1+M22) -> 0 | J22: =SUM(I22) -> 0 | M22: 0 | N22: 0
C23: DEMOLISH EXISTING FLOOR AND BASE FINISH | D23: Patch & Repair for New Finish | E23: 2721.69 | F23: SF | G23: 14 | H23: MH, 3 WORKERS | I23: =E23*N23*(1+M23) -> 0 | J23: =SUM(I23) -> 0 | M23: 0 | N23: 0
C24: DEMOLISH EXISTING FIXTURES | D24: This Includes all tables, and chairs | E24: 15 | F24: EA | G24: 4 | H24: MH, 2 WORKERS | I24: =E24*N24*(1+M24) -> 0 | J24: =SUM(I24) -> 0 | M24: 0 | N24: 0
C25: DEMOLISH EXISTING FIXTURES | D25: This includes all interior fixtures | E25: 371.03 | F25: SF | G25: 6 | H25: MH, 3 WORKERS | I25: =E25*N25*(1+M25) -> 0 | J25: =SUM(I25) -> 0 | M25: 0 | N25: 0
C26: DEMOLISH EXISTING CONDIMENT CART | E26: 1 | F26: EA | G26: 0.5 | H26: MH, 2 WORKERS | I26: =E26*N26*(1+M26) -> 0 | J26: =SUM(I26) -> 0 | M26: 0 | N26: 0
C27: DEMOLISH EXISTING IN-WALL FOOD/BEVERAGE COOLER | E27: 2 | F27: EA | G27: 3 | H27: MH, 3 WORKERS | I27: =E27*N27*(1+M27) -> 0 | J27: =SUM(I27) -> 0 | M27: 0 | N27: 0
C28: DEMOLISH EXISTING INTERIOR FURNITURE & FIXTURES | D28: This includes all tables, chairs, and kitchen fixtures | E28: 11 | F28: EA | G28: 3.2 | H28: MH, 2 WORKERS | I28: =E28*N28*(1+M28) -> 0 | J28: =SUM(I28) -> 0 | M28: 0 | N28: 0
C29: DEMOLISH EXISTING MERCH BASKET | E29: 2 | F29: EA | G29: 1 | H29: MH, 2 WORKERS | I29: =E29*N29*(1+M29) -> 0 | J29: =SUM(I29) -> 0 | M29: 0 | N29: 0
C30: DEMOLISH EXISTING MERCH BAYS | E30: 2 | F30: EA | G30: 2 | H30: MH, 2 WORKERS | I30: =E30*N30*(1+M30) -> 0 | J30: =SUM(I30) -> 0 | M30: 0 | N30: 0
C31: DEMOLISH EXISTING WALL FINISHES | D31: Elevation refer to sheet D102-D103 | E31: 2652.9 | F31: SF | G31: 18 | H31: MH, 3 WORKERS | I31: =E31*N31*(1+M31) -> 0 | J31: =SUM(I31) -> 0 | M31: 0 | N31: 0
C32: REMOVE EXISTING CASEWORK, HANGING DEVICES, AND FASTENERS | D32: All counters in the serving area | E32: 129.18 | F32: SF | G32: 4 | H32: MH, 2 WORKERS | I32: =E32*N32*(1+M32) -> 0 | J32: =SUM(I32) -> 0 | M32: 0 | N32: 0
C33: REMOVE EXISTING DOOR FRAME, AND ASSOCIATED FASTENERS | E33: 9 | F33: EA | G33: 4.5 | H33: MH, 2 WORKERS | I33: =E33*N33*(1+M33) -> 0 | J33: =SUM(I33) -> 0 | M33: 0 | N33: 0
C35: CEILING
C36: DEMOLISH EXISTING MENU BOARD | D36: No details on height (Assumed as per standard of starbucks 35") See Notes for references | E36: 78.75 | F36: SF | G36: 2 | H36: MH, 2 WORKERS | I36: =E36*N36*(1+M36) -> 0 | J36: =SUM(I36) -> 0 | M36: 0 | N36: 0
C37: DEMOLISH EXISTING UPPER CUBBIES | D37: No details on height (Assumed as per standard of starbucks 35") See Notes for references | E37: 78.75 | F37: SF | G37: 2 | H37: MH, 2 WORKERS | I37: =E37*N37*(1+M37) -> 0 | J37: =SUM(I37) -> 0 | M37: 0 | N37: 0
C38: DEMOLISH EXISTING ACT CEILING TILES AND GRID | E38: 1210.9 | F38: SF | G38: 12 | H38: MH, 3 WORKERS | I38: =E38*N38*(1+M38) -> 0 | J38: =SUM(I38) -> 0 | M38: 0 | N38: 0
C39: DEMOLISH HARD LID CEILING, FRAMING AND ASSOCIATED FASTENERS TO BOTTOM OF STRUCTURE ABOVE | E39: 270.7 | F39: SF | G39: 4 | H39: MH, 3 WORKERS | I39: =E39*N39*(1+M39) -> 0 | J39: =SUM(I39) -> 0 | M39: 0 | N39: 0
C41: ITEMS TO RELOCATE
C42: 1 DR U/C FRIDGE | D42: Relocation only, Excluding Installation | E42: 2 | F42: EA | G42: 1.5 | H42: MH, 2 MOVERS | I42: =E42*N42*(1+M42) -> 0 | J42: =SUM(I42) -> 0 | M42: 0 | N42: 0
C43: 2-DR FREEZER | D43: Relocation only, Excluding Installation | E43: 1 | F43: EA | G43: 1.5 | H43: MH, 2 MOVERS | I43: =E43*N43*(1+M43) -> 0 | J43: =SUM(I43) -> 0 | M43: 0 | N43: 0
C44: 2-DR FRIDGE | D44: Relocation only, Excluding Installation | E44: 1 | F44: EA | G44: 1.5 | H44: MH, 2 MOVERS | I44: =E44*N44*(1+M44) -> 0 | J44: =SUM(I44) -> 0 | M44: 0 | N44: 0
C45: 3-COMP SINK & ASSOCIATED ITEMS | D45: Relocation only, Excluding Installation | E45: 1 | F45: EA | G45: 2 | H45: MH, 3 (INCL LEAD) | I45: =E45*N45*(1+M45) -> 0 | J45: =SUM(I45) -> 0 | M45: 0 | N45: 0
C46: BLENDERS | D46: Relocation only, Excluding Installation | E46: 2 | F46: EA | G46: 0.5 | H46: MH, 1 MOVER | I46: =E46*N46*(1+M46) -> 0 | J46: =SUM(I46) -> 0 | M46: 0 | N46: 0
C47: CUP CADDY & DISPENSERS | D47: Relocation only, Excluding Installation | E47: 1 | F47: EA | G47: 0.25 | H47: MH, 1 MOVER | I47: =E47*N47*(1+M47) -> 0 | J47: =SUM(I47) -> 0 | M47: 0 | N47: 0
C48: CUP LABELER | D48: Relocation only, Excluding Installation | E48: 4 | F48: EA | G48: 2 | H48: MH, 1 MOVER | I48: =E48*N48*(1+M48) -> 0 | J48: =SUM(I48) -> 0 | M48: 0 | N48: 0
C49: ESPRESSO MACHINES | D49: Relocation only, Excluding Installation | E49: 2 | F49: EA | G49: 2 | H49: MH, 2 MOVERS | I49: =E49*N49*(1+M49) -> 0 | J49: =SUM(I49) -> 0 | M49: 0 | N49: 0
C50: FOOD CASE | D50: Relocation only, Excluding Installation | E50: 1 | F50: EA | G50: 2 | H50: MH, 3 MOVERS | I50: =E50*N50*(1+M50) -> 0 | J50: =SUM(I50) -> 0 | M50: 0 | N50: 0
C51: GRINDER | D51: Relocation only, Excluding Installation | E51: 1 | F51: EA | G51: 0.5 | H51: MH, 1 MOVER | I51: =E51*N51*(1+M51) -> 0 | J51: =SUM(I51) -> 0 | M51: 0 | N51: 0
C52: ICE BIN | D52: Relocation only, Excluding Installation | E52: 1 | F52: EA | G52: 1 | H52: MH, 2 MOVERS | I52: =E52*N52*(1+M52) -> 0 | J52: =SUM(I52) -> 0 | M52: 0 | N52: 0
C53: METRO RACK | D53: Relocation only, Excluding Installation | E53: 6 | F53: EA | G53: 3 | H53: MH, 1 MOVER | I53: =E53*N53*(1+M53) -> 0 | J53: =SUM(I53) -> 0 | M53: 0 | N53: 0
... C62: WARMING OVENS | D62: Relocation only, Excluding Installation | E62: 2 | F62: EA | G62: 2 | H62: MH, 2 MOVERS | I62: =E62*N62*(1+M62) -> 0 | J62: =SUM(I62) -> 0 | M62: 0 | N62: 0
D63: =C14 -> DEMOLITION | E63: (TOTAL) | I63: =SUM(I16:I62) -> 0 | J63: =SUM(J16:J62) -> 0
D64: OVERHEAD | F64: 0 | J64: =F64*J63 -> 0
D65: SUB-TOTAL | J65: =SUM(J63:J64) -> 0
C67: LANDSCAPING
C68: =Landscaping!A2 -> PLANTS
C69: =Landscaping!A3 -> Mixture of Plants | D69: =Landscaping!B3 -> Sanseviera-Tall, Flowering Annuals-Small, Sweet Potato Vine- Low/Hanging | E69: =Landscaping!C3 -> 7.8 | F69: SF | G69: 0.25 | H69: MH, 2 WORKER | I69: =E69*N69*(1+M69) -> 0 | J69: =SUM(I69) -> 0 | M69: 0 | N69: 0
C70: =Landscaping!A4 -> Bird of Paradise | D70: =Landscaping!B4 -> Tall Height | E70: =Landscaping!C4 -> 1 | F70: EA | G70: 0.25 | H70: MH, 1 WORKER | I70: =E70*N70*(1+M70) -> 0 | J70: =SUM(I70) -> 0 | M70: 0 | N70: 0
C71: =Landscaping!A5 -> Limelight | D71: =Landscaping!B5 -> Medium Height | E71: =Landscaping!C5 -> 2 | F71: EA | G71: 0.25 | H71: MH, 1 WORKER | I71: =E71*N71*(1+M71) -> 0 | J71: =SUM(I71) -> 0 | M71: 0 | N71: 0
C72: =Landscaping!A6 -> ZZ Plant | D72: =Landscaping!B6 -> Medium Height | E72: =Landscaping!C6 -> 2 | F72: EA | G72: 0.25 | H72: MH, 1 WORKER | I72: =E72*N72*(1+M72) -> 0 | J72: =SUM(I72) -> 0 | M72: 0 | N72: 0
C73: =Landscaping!A7 -> Golden Pathos | D73: =Landscaping!B7 -> Low Height | E73: =Landscaping!C7 -> 1 | F73: EA | G73: 0.25 | H73: MH, 1 WORKER | I73: =E73*N73*(1+M73) -> 0 | J73: =SUM(I73) -> 0 | M73: 0 | N73: 0
C74: =Landscaping!A8 -> Prayer Plant | D74: =Landscaping!B8 -> Low Height | E74: =Landscaping!C8 -> 1 | F74: EA | G74: 0.25 | H74: MH, 1 WORKER | I74: =E74*N74*(1+M74) -> 0 | J74: =SUM(I74) -> 0 | M74: 0 | N74: 0
C75: =Landscaping!A9 -> Bird's Nest Fern | D75: =Landscaping!B9 -> Low Height | E75: =Landscaping!C9 -> 1 | F75: EA | G75: 0.25 | H75: MH, 1 WORKER | I75: =E75*N75*(1+M75) -> 0 | J75: =SUM(I75) -> 0 | M75: 0 | N75: 0
C76: =Landscaping!A10 -> Sanseviera | D76: =Landscaping!B10 -> Low Height | E76: =Landscaping!C10 -> 1 | F76: EA | G76: 0.25 | H76: MH, 1 WORKER | I76: =E76*N76*(1+M76) -> 0 | J76: =SUM(I76) -> 0 | M76: 0 | N76: 0
C78: =Landscaping!A12 -> PLANTER
C79: Exterior
C80: =Landscaping!A14 -> Auroa Clay Outdoor Planters Large | D80: =Landscaping!B14 -> furnished by SB and install by GC | E80: =Landscaping!C14 -> 1 | F80: EA | G80: 1.25 | H80: MH, 2 WORKER | I80: =E80*N80*(1+M80) -> 0 | J80: =SUM(I80) -> 0 | M80: 0 | N80: 0
C81: Interior
C82: =Landscaping!A16 -> Parker Pedestal Med Planter-Alabaster, Standard Entry | D82: =Landscaping!B16 -> furnished by SB and install by GC | E82: =Landscaping!C16 -> 1 | F82: EA | G82: 1 | H82: MH, 2 WORKER | I82: =E82*N82*(1+M82) -> 0 | J82: =SUM(I82) -> 0 | M82: 0 | N82: 0
C83: =Landscaping!A17 -> Flueted Ceramic- TableTop White-Small | D83: =Landscaping!B17 -> furnished by SB and install by GC | E83: =Landscaping!C17 -> 2 | F83: EA | G83: 0.25 | H83: MH, 1 WORKER
C84: =Landscaping!A18 -> Flueted Ceramic- TableTop White-Medium | D84: =Landscaping!B18 -> furnished by SB and install by GC | E84: =Landscaping!C18 -> 2 | F84: EA | G84: 0.25 | H84: MH, 1 WORKER | I84: =E84*N84*(1+M84) -> 0 | J84: =SUM(I84) -> 0 | M84: 0 | N84: 0
D85: =Landscaping!B19 -> 0
C86: =Landscaping!A20 -> MISCELLANEOUS
C87: =Landscaping!A21 -> Umbrella Base | D87: =Landscaping!B21 -> furnished by SB and install by GC | E87: =Landscaping!C21 -> 1 | F87: EA | G87: 0.5 | H87: MH, 2 WORKER | I87: =E87*N87*(1+M87) -> 0 | J87: =SUM(I87) -> 0 | M87: 0 | N87: 0
C88: =Landscaping!A22 -> Umbrella without Valance | D88: =Landscaping!B22 -> furnished by SB and install by GC | E88: =Landscaping!C22 -> 1 | F88: EA | G88: 0.75 | H88: MH, 2 WORKER | I88: =E88*N88*(1+M88) -> 0 | J88: =SUM(I88) -> 0 | M88: 0 | N88: 0
D89: =C67 -> LANDSCAPING | E89: (TOTAL) | I89: =SUM(I68:I88) -> 0 | J89: =SUM(J68:J88) -> 0
D90: OVERHEAD | F90: 0 | J90: =F90*J89 -> 0
D91: SUB-TOTAL | J91: =SUM(J89:J90) -> 0
C93: EXTERIOR SIDING
C94: ='Exterior Siding'!B20 -> Veneer Siding
C95: ='Exterior Siding'!B27 -> Brick Veneer | D95: ='Exterior Siding'!C27 -> Patching and Repair | E95: ='Exterior Siding'!D27 -> 164 | F95: ='Exterior Siding'!E27 -> SF | G95: 7.65 | H95: MH, 2 WORKER | I95: =E95*N95*(1+M95) -> 0 | J95: =I95 -> 0 | M95: 0 | N95: 0
D97: =C93 -> EXTERIOR SIDING | E97: (TOTAL) | I97: =SUM(I94:I96) -> 0 | J97: =SUM(J94:J96) -> 0
D98: OVERHEAD | F98: 0 | J98: =F98*J97 -> 0
D99: SUB-TOTAL | J99: =SUM(J97:J98) -> 0
C101: EXTERIOR PAINTING
C102: ='Exterior Painting'!B7 -> EXTERIOR FINISHES
C103: ='Exterior Painting'!B8 -> Exterior Patio Railing Finishes, 2 Coats Stain
C104: ='Exterior Painting'!B11 -> Exterior Patio Railings | E104: ='Exterior Painting'!C11 -> 94.44 | F104: ='Exterior Painting'!D11 -> LF | G104: 7.4 | H104: MH, 2 WORKER | I104: =E104*N104*(1+M104) -> 0 | J104: =I104 -> 0 | M104: 0 | N104: 0
C105: ='Exterior Painting'!B12 -> Exterior Patio Post Finishes, Primer + 2 Coats Paint
C106: ='Exterior Painting'!B16 -> Exterior Patio Post | E106: ='Exterior Painting'!C16 -> 85.02 | F106: ='Exterior Painting'!D16 -> LF | G106: 7.7 | H106: MH, 1 WORKER | I106: =E106*N106*(1+M106) -> 0 | J106: =I106 -> 0 | M106: 0 | N106: 0
D107: =C101 -> EXTERIOR PAINTING | E107: (TOTAL) | I107: =SUM(I102:I106) -> 0 | J107: =SUM(J102:J106) -> 0
D108: OVERHEAD | F108: 0 | J108: =F108*J107 -> 0
D109: SUB-TOTAL | J109: =SUM(J107:J108) -> 0
C111: METAL STUD FRAMING
C112: =FDI!B76 -> METAL STUD
C113: =FDI!B77 -> 1-T-N, Partial Height=12' | J113: =I113 -> 0
C114: =FDI!B78 -> 1-1/2" 20ga Metal Stud x 12' at 16" OC | E114: =FDI!E78 -> 4 | F114: =FDI!F78 -> EA | G114: =FDI!M78 -> 1 | H114: MH, 4 WORKERS | I114: =E114*N114*(1+M114) -> 0 | J114: =I114 -> 0 | M114: 0 | N114: 0
C115: =FDI!B79 -> 1-1/2" 20ga U-Track x 10' | E115: =FDI!E79 -> 1 | F115: =FDI!F79 -> EA | H115: MH, 4 WORKERS | I115: =E115*N115*(1+M115) -> 0 | J115: =I115 -> 0 | M115: 0 | N115: 0
C116: =FDI!B80 -> 1-1/2" 20ga Metal Stud Bracing x 8' at 48" OC | E116: =FDI!E80 -> 1 | F116: =FDI!F80 -> EA | H116: MH, 4 WORKERS | I116: =E116*N116*(1+M116) -> 0 | J116: =I116 -> 0 | M116: 0 | N116: 0
C118: =FDI!B82 -> 2-F-N & 3-F-N, Full Height=20'
C119: =FDI!B83 -> 3-5/8" 20ga Metal Stud x 20' at 16" OC | E119: =FDI!E83 -> 34 | F119: =FDI!F83 -> EA | G119: =FDI!M83 -> 6 | H119: MH, 4 WORKERS | I119: =E119*N119*(1+M119) -> 0 | J119: =I119 -> 0 | M119: 0 | N119: 0
C120: =FDI!B84 -> 3-5/8" 20ga Deflection Track x 10' | E120: =FDI!E84 -> 5 | F120: =FDI!F84 -> EA | H120: MH, 4 WORKERS | I120: =E120*N120*(1+M120) -> 0 | J120: =I120 -> 0 | M120: 0 | N120: 0
C121: =FDI!B85 -> 3-5/8" 20ga U-Track x 10' | E121: =FDI!E85 -> 5 | F121: =FDI!F85 -> EA | H121: MH, 4 WORKERS | I121: =E121*N121*(1+M121) -> 0 | J121: =I121 -> 0 | M121: 0 | N121: 0
C123: =FDI!B87 -> 2-P-N, Partial Height=12'
C124: =FDI!B88 -> 3-5/8" 20ga Metal Stud x 12' at 16" OC | E124: =FDI!E88 -> 25 | F124: =FDI!F88 -> EA | G124: =FDI!M88 -> 2 | H124: MH, 4 WORKERS | I124: =E124*N124*(1+M124) -> 0 | J124: =I124 -> 0 | M124: 0 | N124: 0
C125: =FDI!B89 -> 3-5/8" 20ga U-Track x 10' | E125: =FDI!E89 -> 7 | F125: =FDI!F89 -> EA | H125: MH, 4 WORKERS | I125: =E125*N125*(1+M125) -> 0 | J125: =I125 -> 0 | M125: 0 | N125: 0
...

Sheet Flooring & Tile
B1: Flooring & Tile Finishes
B3: BASE TAKE-OFF
B5: Unit Name | C5: Product | D5: Qty by Unit | E5: Waste Add-on | G5: Total | J5: MANHOURS/SF | K5: TOTAL MANHOURS
D6: NET
B7: 19795 | C7: Polyvinyl Floor Tile - Eco-Grip - Pewter - 60" x 96" x 1/4" thk | D7: 98.7 | E7: =D7*$F$6 -> 0 | G7: =E7 -> 0 | H7: SY | J7: 1.08 | K7: =ROUNDUP(J7*D7,0) -> 107
B8: 20230 | C8: Floor Tile - I COCCI - Graphite - 24" x 24" (Installation only) | D8: 1697.4 | E8: =D8*$F$6 -> 0 | G8: =E8 -> 0 | H8: SF | J8: 0.14 | K8: =ROUNDUP(J8*D8,0) -> 238
B9: 20267 | C9: Wall Tile - French Clay - Bronzage - 12" x 24" - Vertical Stacked (Installation only) | D9: 335.1 | E9: =D9*$F$6 -> 0 | G9: =E9 -> 0 | H9: SF | J9: 0.14 | K9: =ROUNDUP(J9*D9,0) -> 47
B10: 24559 | C10: Wall Tile - Flatiron - Olivia - Gloss - 2.5" x 9" Vertical Stacked (Installation only) | D10: 156.9 | E10: =D10*$F$6 -> 0 | G10: =E10 -> 0 | H10: SF | J10: 0.14 | K10: =ROUNDUP(J10*D10,0) -> 22
B11: x0409 | C11: Tile Base - Daltile Color Wheel - A3361MOD, Matte Black k711 (Installation only) | D11: 42.9 | E11: =D11*$F$6 -> 0 | G11: =E11 -> 0 | H11: LF | J11: 0.3 | K11: =ROUNDUP(J11*D11,0) -> 13
B12: 11403 | C12: Tile Base - Nero - 6"x12" (Installation only) | D12: 189.3 | E12: =D12*$F$6 -> 0 | G12: =E12 -> 0 | H12: LF | J12: 0.12 | K12: =ROUNDUP(J12*D12,0) -> 23
B13: 19795 | C13: Tile Base - Polyvinyl Floor Tile - Eco-Grip - Pewter - 6" | D13: 243.6 | E13: =D13*$F$6 -> 0 | G13: =E13 -> 0 | H13: LF | J13: 0.3 | K13: =ROUNDUP(J13*D13,0) -> 74
B14: x0404 | C14: Schluter Base - Dilex AHK-AGRB - Brushed Graphite | D14: 58.4 | E14: =D14*$F$6 -> 0 | G14: =E14 -> 0 | H14: LF | J14: 0.1 | K14: =ROUNDUP(J14*D14,0) -> 6
B15: x0801 | C15: Trim - Schluter Jolly Edge Trim - Aluminum Matte Black - Code: J100MGS | D15: 4.09 | E15: =D15*$F$6 -> 0 | G15: =E15 -> 0 | H15: LF | J15: 0.05 | K15: =ROUNDUP(J15*D15,0) -> 1
C16: Schluter Transition Strip for Tile to Eco-Grip | D16: 16.3 | E16: =D16*$F$6 -> 0 | G16: =E16 -> 0 | H16: LF | J16: 0.06 | K16: =ROUNDUP(J16*D16,0) -> 1
C17: Transition for Walk Off Mat to Tile - Schluter Systems - Edge Metal - Schiene - 3/8" | D17: 16.1 | E17: =D17*$F$6 -> 0 | G17: =E17 -> 0 | H17: LF | J17: 0.05 | K17: =ROUNDUP(J17*D17,0) -> 1
B21: NOTES:
B22: Flooring & Tile
B23: Finish Material Schedule per print I603.
B24: Items that are provided by SB and to be installed only by GC ; Tile 20230, tile base x0409, tile base 11403, tile 24599 and tile 20267.
B25: Polyvinyl floor tile is considered as SY unit in the takeoff ; size sheets: 60" x 96" x 1/4" thk.
B26: Polyvinyl floor tile base is considered as LF unit in the takeoff.
B27: Walk Off Mat is existing to remain per plan notes.

Sheet FDI
B3: Description | C3: Location | D3: QTY (LF) | E3: Drywall Height (LF) - Side 1 | F3: Drywall Height (LF) - Side 2 | G3: Side 1 (Interior Side) | K3: Side 2 (Exterior Side) | O3: Multiplier | P3: Wall Area (SF) | T3: STUDS
G4: Sheathing Type | H4: THK | I4: Finish Level | J4: No. of Layers | K4: Sheathing Type | L4: THK | M4: Finish Level | N4: No. of Layers | P4: Side 1 | Q4: Side 2 | R4: 1 1/2" 20ga x 12' @ 16"OC | S4: 1 1/2" 20ga Bracing x 8' @ 48"OC | T4: 3 5/8" 20ga x 20' @ 16"OC | U4: 3 5/8" 16ga x 14' @ 16"OC | V4: 3 5/8" 20ga x 12' @ 16"OC | W4: 3 5/8" 20ga Bracing x 8' @ 48"OC | X4: 3 5/8" 16ga x 2' @ 16"OC | Y4: 6" 20ga x 20' @ 16"OC | Z4: 6" 20ga x 14' @ 16"OC | AA4: 6" 20ga x 12' @ 16"OC | AB4: 6" 20ga Bracing x 8' @ 48"OC
B5: WALLS
B6: PHASE 1
B7: 1-T-N | C7: Interior Wall | D7: 4 | E7: 12 | G7: 5/8" Gypsum Board Type X | H7: 45785 | I7: 4 | J7: 1 | O7: 1 | P7: =D7*E7*J7*O7 -> 48 | Q7: =D7*F7*N7*O7 -> 0 | R7: =D7 -> 4 | S7: =D7 -> 4
B8: 2-F-N | C8: Interior Wall | D8: 27 | E8: 19 | G8: 5/8" Gypsum Board Type X | H8: 45785 | I8: 4 | J8: 1 | O8: 1 | P8: =D8*E8*J8*O8 -> 513 | Q8: =D8*F8*N8*O8 -> 0 | T8: =D8 -> 27
B9: 2-P-N | C9: Interior Wall | D9: 32 | E9: 12 | G9: 5/8" Gypsum Board Type X | H9: 45785 | I9: 4 | J9: 1 | O9: 1 | P9: =D9*E9*J9*O9 -> 384 | Q9: =D9*F9*N9*O9 -> 0 | V9: =D9 -> 32
B10: 2-T-N | C10: Interior Wall | D10: 18 | E10: 12 | G10: 5/8" Gypsum Board Type X | H10: 45785 | I10: 4 | J10: 1 | O10: 1 | P10: =D10*E10*J10*O10 -> 216 | Q10: =D10*F10*N10*O10 -> 0 | V10: =D10 -> 18 | W10: =D10 -> 18
B11: 3-F-N | C11: Interior Wall | D11: 17 | E11: 19 | F11: 12 | G11: 5/8" Gypsum Board Type X | H11: 45785 | I11: 4 | J11: 1 | K11: 5/8" Gypsum Board Type X | L11: 45785 | M11: 4 | N11: 1 | O11: 1 | P11: =D11*E11*J11*O11 -> 323 | Q11: =D11*F11*N11*O11 -> 204 | T11: =D11 -> 17
B12: 3-P-N | C12: Interior Wall | D12: 3 | E12: 2 | F12: 2 | G12: 5/8" Gypsum Board Type X | H12: 45785 | I12: 4 | J12: 1 | K12: 5/8" Gypsum Board Type X | L12: 45785 | M12: 4 | N12: 1 | O12: 1 | P12: =D12*E12*J12*O12 -> 6 | Q12: =D12*F12*N12*O12 -> 6 | X12: =D12 -> 3
B13: 3-T-N | C13: Interior Wall | D13: 44 | E13: 12 | F13: 12 | G13: 5/8" Gypsum Board Type X | H13: 45785 | I13: 4 | J13: 1 | K13: 5/8" Gypsum Board Type X | L13: 45785 | M13: 4 | N13: 1 | O13: 1 | P13: =D13*E13*J13*O13 -> 528 | Q13: =D13*F13*N13*O13 -> 528 | V13: =D13 -> 44 | W13: =D13 -> 44
B14: 3-T-N-H | C14: Interior Wall | D14: 7 | E14: 14 | F14: 14 | G14: 5/8" Gypsum Board Type X | H14: 45785 | I14: 4 | J14: 1 | K14: 5/8" Gypsum Board Type X | L14: 45785 | M14: 4 | N14: 1 | O14: 1 | P14: =D14*E14*J14*O14 -> 98 | Q14: =D14*F14*N14*O14 -> 98 | U14: =D14 -> 7 | W14: =D14 -> 7
B15: 4-F-N | C15: Interior Wall | D15: 3 | E15: 19 | F15: 12 | G15: 5/8" Gypsum Board Type X | H15: 45785 | I15: 4 | J15: 1 | K15: 5/8" Gypsum Board Type X | L15: 45785 | M15: 4 | N15: 1 | O15: 1 | P15: =D15*E15*J15*O15 -> 57 | Q15: =D15*F15*N15*O15 -> 36 | Y15: =D15 -> 3
B16: 4-T-N | C16: Interior Wall | D16: 9 | E16: 14 | F16: 14 | G16: 5/8" Gypsum Board Type X | H16: 45785 | I16: 4 | J16: 1 | K16: 5/8" Gypsum Board Type X | L16: 45785 | M16: 4 | N16: 1 | O16: 1 | P16: =D16*E16*J16*O16 -> 126 | Q16: =D16*F16*N16*O16 -> 126 | Z16: =D16 -> 9 | AB16: =D16 -> 9
B17: 4-T-N | C17: Interior Wall | D17: 33 | E17: 12 | F17: 12 | G17: 5/8" Gypsum Board Type X | H17: 45785 | I17: 4 | J17: 1 | K17: 5/8" Gypsum Board Type X | L17: 45785 | M17: 4 | N17: 1 | O17: 1 | P17: =D17*E17*J17*O17 -> 396 | Q17: =D17*F17*N17*O17 -> 396 | AA17: =D17 -> 33 | AB17: =D17 -> 33
B18: 5-T-N | C18: Interior Wall | D18: 10 | E18: 12 | G18: 5/8" Gypsum Board Type X | H18: 45785 | I18: 4 | J18: 1 | O18: 1 | P18: =D18*E18*J18*O18 -> 120 | Q18: =D18*F18*N18*O18 -> 0 | AA18: =D18 -> 10 | AB18: =D18 -> 10
B19: GWB TYPE X MR | C19: Work Room, Partner Area | D19: 16 | E19: 14 | G19: 5/8" Gypsum Board Type X MR | H19: 45785 | I19: 4 | J19: 1 | O19: 1 | P19: =D19*E19*J19*O19 -> 224 | Q19: =D19*F19*N19*O19 -> 0
B20: GWB TYPE X MR | C20: Work Room, Partner Area | D20: 105 | E20: 12 | G20: 5/8" Gypsum Board Type X MR | H20: 45785 | I20: 4 | J20: 1 | O20: 1 | P20: =D20*E20*J20*O20 -> 1260 | Q20: =D20*F20*N20*O20 -> 0
B21: 14 CBB | C21: Backbar | D21: 65 | E21: 12 | G21: 1/4" Cement Backer Board | H21: 45661 | J21: 1 | O21: 1 | P21: =D21*E21*J21*O21 -> 780 | Q21: =D21*F21*N21*O21 -> 0
O22: =G7 -> 5/8" Gypsum Board Type X | P22: =SUMIF($G$7:$G$21,O22,$P$7:$P$21) -> 2815 | Q22: =SUMIF($K$7:$K$21,O22,$Q$7:$Q$21) -> 1394 | R22: =SUM(R7:R20) -> 4 | S22: =SUM(S7:S20) -> 4 | T22: =SUM(T7:T20) -> 44 | U22: =SUM(U7:U20) -> 7 | V22: =SUM(V7:V20) -> 94 | W22: =SUM(W7:W20) -> 69 | X22: =SUM(X7:X20) -> 3 | Y22: =SUM(Y7:Y20) -> 3 | ... AB22: =SUM(AB7:AB20) -> 52
O23: =G19 -> 5/8" Gypsum Board Type X MR | P23: =SUMIF($G$7:$G$21,O23,$P$7:$P$21) -> 1484 | Q23: =SUMIF($K$7:$K$21,O23,$Q$7:$Q$21) -> 0
O24: =G21 -> 1/4" Cement Backer Board | P24: =SUMIF($G$7:$G$21,O24,$P$7:$P$21) -> 780 | Q24: =SUMIF($K$7:$K$21,O24,$Q$7:$Q$21) -> 0
B25: Description | C25: Location | D25: Perimeter/ Length (LF) | E25: Area (SF) | F25: Height (LF) | G25: Side 1 | J25: Ceiling Area (SF)
G27: Sheathing Type | H27: Finish Level | I27: No. of Layers | J27: Side 1 | K27: STUD
B28: Ceiling | K28: 3 5/8" 20ga x 12' @ 16"OC | L28: 3 5/8" 20ga Bracing x 12' @ 48"OC | M28: 3 5/8" 20ga x 1' @ 16"OC | N28: 3 5/8" 20ga x 10' @ 16"OC | O28: (2) 6" 16ga CSJ x 8' @ 8"OC | P28: (2) 6" 16ga x 6' @ 8"OC
B29: PHASE 1
B30: Gypsum Board Ceiling | E30: 779 | G30: 5/8" Gypsum Board Type X | H30: 4 | I30: 1 | J30: =E30*I30 -> 779
B31: Soffit, H=4' | D31: 88 | E31: =D31*F31 -> 352 | F31: 4 | G31: 5/8" Gypsum Board Type X | H31: 4 | I31: 1 | J31: =E31*I31 -> 352 | K31: =D31 -> 88 | L31: =D31 -> 88
B32: Soffit, H=1' | D32: 117 | E32: =D32*F32 -> 117 | F32: 1 | G32: 5/8" Gypsum Board Type X | H32: 4 | I32: 1 | J32: =E32*I32 -> 117 | M32: =D32 -> 117
B33: Header, H=1' | D33: 34 | E33: =D33*F33 -> 34 | F33: 1 | G33: 5/8" Gypsum Board Type X | H33: 4 | I33: 1 | J33: =E33*I33 -> 34 | M33: =D33 -> 34
B34: Box Header, 2s, H=9' | D34: 9 | E34: =D34*F34*2 -> 162 | F34: 9 | G34: 5/8" Gypsum Board Type X | H34: 4 | I34: 1 | J34: =E34*I34 -> 162 | N34: =D34 -> 9
B35: 12 CBB & 58 GWB Type X MR | C35: Water Heater Shelf | D35: =3+2/12 -> 3.1666667 | E35: 20 | F35: =6+3/12 -> 6.25 | G35: 5/8" Gypsum Board Type X MR | H35: 4 | I35: 1 | J35: =E35*I35 -> 20 | O35: =D35 -> 3.1666667
D36: =3+2/12 -> 3.1666667 | E36: 20 | F36: =6+3/12 -> 6.25 | G36: 1/2" Cement Backer Board | I36: 1 | J36: =E36*I36 -> 20
B37: 58 GWB Type X | C37: Water Heater Shelf | D37: 5 | E37: =D37*F37*2 -> 60 | F37: 6 | G37: 5/8" Gypsum Board Type X | H37: 4 | I37: 1 | J37: =E37*I37 -> 60 | P37: =D37 -> 5
I38: =G30 -> 5/8" Gypsum Board Type X | J38: =SUMIF($G$30:$G$36,I38,$J$30:$J$36) -> 1444 | K38: =SUM(K30:K37) -> 88 | L38: =SUM(L30:L37) -> 88 | M38: =SUM(M30:M37) -> 151 | N38: =SUM(N30:N37) -> 9 | O38: =SUM(O30:O37) -> 3.1666667 | P38: =SUM(P30:P37) -> 5
I39: =G35 -> 5/8" Gypsum Board Type X MR | J39: =SUMIF($G$30:$G$36,I39,$J$30:$J$36) -> 20
I40: =G36 -> 1/2" Cement Backer Board | J40: =SUMIF($G$30:$G$36,I40,$J$30:$J$36) -> 20
B41: Description | C41: Location | D41: AREA (SF) | F41: QTY | H41: Waste Add-on
B43: ACT | H43: 1.03
B46: FRAMING | C46: Location | D46: QTY | F46: Waste Add-on
B47: Jamb Studs and Headers
B48: 6" 20ga Metal Stud x 12' | D48: =2*2+2 -> 6 | E48: EA | F48: =ROUNDUP((D48*$F$47),0) -> 0 | G48: =E48 -> EA
B49: 3 5/8" 20ga U-Track x 10' | D49: =D48 -> 6 | E49: EA | F49: =ROUNDUP((D49*$F$47),0) -> 0 | G49: =E49 -> EA
B50: 3 5/8" 20ga Metal Stud x 12' | D50: =4*2 -> 8 | E50: EA | F50: =ROUNDUP((D50*$F$47),0) -> 0 | G50: =E50 -> EA
B52: Miscellaneous | F52: Waste Add-on
B53: Corner Beads x 10' | D53: =27+2 -> 29 | E53: EA | F53: =ROUNDUP((D53*$F$47),0) -> 0 | G53: =E53 -> EA
B54: Corner Beads x 10' | C54: Soffit, Header | D54: =ROUNDUP(SUM(D31:D33,D34*2)/10,0) -> 26 | E54: EA | F54: =ROUNDUP((D54*$F$47),0) -> 0 | G54: =E54 -> EA
B55: Corner Beads x 12' | D55: 7 | E55: EA | F55: =ROUNDUP((D55*$F$47),0) -> 0 | G55: =E55 -> EA
B57: SUMMARY | G57: Waste Add-on | L57: Productivity Rate per hour for 1 | M57: TOTAL hrs for 4 workers
B58: Description | C58: QTY
B59: WALLS
B60: =O22 -> 5/8" Gypsum Board Type X | C60: =SUM(P22:Q22)-C61 -> 2725 | D60: SF | G60: =ROUNDUP((C60*$G$58),0) -> 0 | H60: =D60 -> SF | L60: 15 | M60: =ROUNDUP(C60/(L60*4),0) -> 46
B61: =O23 -> 5/8" Gypsum Board Type X MR | C61: =SUM(P23:Q23) -> 1484 | D61: SF | G61: =ROUNDUP((C61*$G$58),0) -> 0 | H61: =D61 -> SF | L61: 15 | M61: =ROUNDUP(C61/(L61*4),0) -> 25
B62: =O24 -> 1/4" Cement Backer Board | C62: =SUM(P24:Q24) -> 780 | D62: SF | G62: =ROUNDUP((C62*$G$58),0) -> 0 | H62: =D62 -> SF | L62: 25 | M62: =ROUNDUP(C62/(L62*4),0) -> 8
B64: CEILINGS
B65: =I38 -> 5/8" Gypsum Board Type X | C65: =J38 -> 1444 | D65: SF | G65: =ROUNDUP((C65*$G$58),0) -> 0 | H65: =D65 -> SF | L65: 15 | M65: =ROUNDUP(C65/(L65*4),0) -> 25
B66: =I40 -> 1/2" Cement Backer Board | C66: =J40 -> 20 | D66: SF | G66: =ROUNDUP((C66*$G$58),0) -> 0 | H66: =D66 -> SF | L66: 25 | M66: =ROUNDUP(C66/(L66*4),0) -> 1
B67: Suspended Ceiling System | C67: =C65 -> 1444 | D67: SF | G67: =ROUNDUP((C67*$G$58),0) -> 0 | H67: =D67 -> SF | L67: 20 | M67: =ROUNDUP(C67/(L67*4),0) -> 19
B69: MISCELLANEOUS
B70: Corner Beads x 10' | C70: =SUM(D53:D54) -> 55 | D70: EA | E70: =C70 -> 55 | F70: EA | G70: =ROUNDUP((C70*$G$58),0) -> 0 | H70: =D70 -> EA | I70: =ROUNDUP((E70*$G$58),0) -> 0 | J70: =F70 -> EA
B71: Corner Beads x 12' | C71: =D55 -> 7 | D71: EA | E71: =C71 -> 7 | F71: EA | G71: =ROUNDUP((C71*$G$58),0) -> 0 | H71: =D71 -> EA | I71: =ROUNDUP((E71*$G$58),0) -> 0 | J71: =F71 -> EA
B72: White Dot-Wespac 3.5 gal | C72: =ROUNDUP(SUM(C60:C61,C65)/400,0) -> 15 | D72: BOX | E72: =C72 -> 15 | F72: BOX | G72: =ROUNDUP((C72*$G$58),0) -> 0 | H72: =D72 -> BOX | I72: =ROUNDUP((E72*$G$58),0) -> 0 | J72: =F72 -> BOX
B73: Tape Paper 500 Ft Roll | C73: =ROUNDUP(SUM(C60:C61,C65)/1400,0) -> 5 | D73: ROLLS | E73: =C73 -> 5 | F73: ROLLS | G73: =ROUNDUP((C73*$G$58),0) -> 0 | H73: =D73 -> ROLLS | I73: =ROUNDUP((E73*$G$58),0) -> 0 | J73: =F73 -> ROLLS
B74: Fine Drywall Screws 1 5/8" Pointers (25lb) | C74: =ROUNDUP(SUM(C60:C61,C65)/7500,0) -> 1 | D74: BOX | E74: =C74 -> 1 | F74: BOX | G74: =ROUNDUP((C74*$G$58),0) -> 0 | H74: =D74 -> BOX | I74: =ROUNDUP((E74*$G$58),0) -> 0 | J74: =F74 -> BOX
B76: METAL STUD
B77: 1-T-N, Partial Height=12'
B78: 1-1/2" 20ga Metal Stud x 12' at 16" OC | C78: =R22 -> 4 | D78: LF | E78: =ROUNDUP(C78/1.33,0) -> 4 | F78: EA | G78: =ROUNDUP((C78*$G$58),0) -> 0 | H78: =D78 -> LF | I78: =ROUNDUP((E78*$G$58),0) -> 0 | J78: =F78 -> EA | L78: 4 | M78: =ROUNDUP(C78/(L78*4),0) -> 1
B79: 1-1/2" 20ga U-Track x 10' | C79: =C78*2 -> 8 | D79: LF | E79: =ROUNDUP(C79/10,0) -> 1 | F79: EA | G79: =ROUNDUP((C79*$G$58),0) -> 0 | H79: =D79 -> LF | I79: =ROUNDUP((E79*$G$58),0) -> 0 | J79: =F79 -> EA
B80: 1-1/2" 20ga Metal Stud Bracing x 8' at 48" OC | C80: =S22 -> 4 | D80: LF | E80: =ROUNDUP(C80/4,0) -> 1 | F80: EA | G80: =ROUNDUP((C80*$G$58),0) -> 0 | H80: =D80 -> LF | I80: =ROUNDUP((E80*$G$58),0) -> 0 | J80: =F80 -> EA
B82: 2-F-N & 3-F-N, Full Height=20'
B83: 3-5/8" 20ga Metal Stud x 20' at 16" OC | C83: =T22 -> 44 | D83: LF | E83: =ROUNDUP(C83/1.33,0) -> 34 | F83: EA | G83: =ROUNDUP((C83*$G$58),0) -> 0 | H83: =D83 -> LF | I83: =ROUNDUP((E83*$G$58),0) -> 0 | J83: =F83 -> EA | L83: 2 | M83: =ROUNDUP(C83/(L83*4),0) -> 6
B84: 3-5/8" 20ga Deflection Track x 10' | C84: =C83 -> 44 | D84: LF | E84: =ROUNDUP(C84/10,0) -> 5 | F84: EA | G84: =ROUNDUP((C84*$G$58),0) -> 0 | H84: =D84 -> LF | I84: =ROUNDUP((E84*$G$58),0) -> 0 | J84: =F84 -> EA
B85: 3-5/8" 20ga U-Track x 10' | C85: =C84 -> 44 | D85: LF | E85: =ROUNDUP(C85/10,0) -> 5 | F85: EA | G85: =ROUNDUP((C85*$G$58),0) -> 0 | H85: =D85 -> LF | I85: =ROUNDUP((E85*$G$58),0) -> 0 | J85: =F85 -> EA
B87: 2-P-N, Partial Height=12'
B88: 3-5/8" 20ga Metal Stud x 12' at 16" OC | C88: =V9 -> 32 | D88: LF | E88: =ROUNDUP(C88/1.33,0) -> 25 | F88: EA | G88: =ROUNDUP((C88*$G$58),0) -> 0 | H88: =D88 -> LF | I88: =ROUNDUP((E88*$G$58),0) -> 0 | J88: =F88 -> EA | L88: 4 | M88: =ROUNDUP(C88/(L88*4),0) -> 2
B89: 3-5/8" 20ga U-Track x 10' | C89: =C88*2 -> 64 | D89: LF | E89: =ROUNDUP(C89/10,0) -> 7 | F89: EA | G89: =ROUNDUP((C89*$G$58),0) -> 0 | H89: =D89 -> LF | I89: =ROUNDUP((E89*$G$58),0) -> 0 | J89: =F89 -> EA
B91: 2-T-N & 3-T-N, Parital Height=12'
B92: 3-5/8" 20ga Metal Stud x 12' at 16" OC | C92: =V22-V9 -> 62 | D92: LF | E92: =ROUNDUP(C92/1.33,0) -> 47 | F92: EA | G92: =ROUNDUP((C92*$G$58),0) -> 0 | H92: =D92 -> LF | I92: =ROUNDUP((E92*$G$58),0) -> 0 | J92: =F92 -> EA | L92: 4 | M92: =ROUNDUP(C92/(L92*4),0) -> 4
B93: 3-5/8" 20ga U-Track x 10' | C93: =C92*2 -> 124 | D93: LF | E93: =ROUNDUP(C93/10,0) -> 13 | F93: EA | G93: =ROUNDUP((C93*$G$58),0) -> 0 | H93: =D93 -> LF | I93: =ROUNDUP((E93*$G$58),0) -> 0 | J93: =F93 -> EA
B94: 3-5/8" 20ga Metal Stud Bracing x 8' at 48" OC | C94: =W22-W14 -> 62 | D94: LF | E94: =ROUNDUP(C94/4,0) -> 16 | F94: EA | G94: =ROUNDUP((C94*$G$58),0) -> 0 | H94: =D94 -> LF | I94: =ROUNDUP((E94*$G$58),0) -> 0 | J94: =F94 -> EA
B96: 3-P-N, Parital Height=2'
B97: 3-5/8" 16ga Metal Stud x 8' at 16" OC | C97: =X12 -> 3 | D97: LF | E97: =ROUNDUP(C97/4/1.33,0) -> 1 | F97: EA | G97: =ROUNDUP((C97*$G$58),0) -> 0 | H97: =D97 -> LF | I97: =ROUNDUP((E97*$G$58),0) -> 0 | J97: =F97 -> EA | L97: 2 | M97: =ROUNDUP(C97/(L97*4),0) -> 1
B98: 3-5/8" 16ga U-Track x 10' | C98: =C97*2 -> 6 | D98: LF | E98: =ROUNDUP(C98/10,0) -> 1 | F98: EA | G98: =ROUNDUP((C98*$G$58),0) -> 0 | H98: =D98 -> LF | I98: =ROUNDUP((E98*$G$58),0) -> 0 | J98: =F98 -> EA
B100: 3-T-N-H, Parital Height=14'
B101: 3-5/8" 16ga Metal Stud x 14' at 16" OC | C101: =U22 -> 7 | D101: LF | E101: =ROUNDUP(C101/1.33,0) -> 6 | F101: EA | G101: =ROUNDUP((C101*$G$58),0) -> 0 | H101: =D101 -> LF | I101: =ROUNDUP((E101*$G$58),0) -> 0 | J101: =F101 -> EA | L101: 2 | M101: =ROUNDUP(C101/(L101*4),0) -> 1
B102: 3-5/8" 16ga U-Track x 10' | C102: =C101*2 -> 14 | D102: LF | E102: =ROUNDUP(C102/10,0) -> 2 | F102: EA | G102: =ROUNDUP((C102*$G$58),0) -> 0 | H102: =D102 -> LF | I102: =ROUNDUP((E102*$G$58),0) -> 0 | J102: =F102 -> EA
B103: 3-5/8" 20ga Metal Stud Bracing x 8' at 48" OC | C103: =W14 -> 7 | D103: LF | E103: =ROUNDUP(C103/4,0) -> 2 | F103: EA | G103: =ROUNDUP((C103*$G$58),0) -> 0 | H103: =D103 -> LF | I103: =ROUNDUP((E103*$G$58),0) -> 0 | J103: =F103 -> EA
B105: 4-F-N, Full Height=20'
B106: 6" 20ga Metal Stud x 20' at 16" OC | C106: =Y22 -> 3 | D106: LF | E106: =ROUNDUP(C106/1.33,0) -> 3 | F106: EA | G106: =ROUNDUP((C106*$G$58),0) -> 0 | H106: =D106 -> LF | I106: =ROUNDUP((E106*$G$58),0) -> 0 | J106: =F106 -> EA | L106: 2 | M106: =ROUNDUP(C106/(L106*4),0) -> 1
B107: 6" 20ga Deflection Track x 10' | C107: =C106 -> 3 | D107: LF | E107: =ROUNDUP(C107/10,0) -> 1 | F107: EA | G107: =ROUNDUP((C107*$G$58),0) -> 0 | H107: =D107 -> LF | I107: =ROUNDUP((E107*$G$58),0) -> 0 | J107: =F107 -> EA
B108: 6" 20ga U-Track x 10' | C108: =C107 -> 3 | D108: LF | E108: =ROUNDUP(C108/10,0) -> 1 | F108: EA | G108: =ROUNDUP((C108*$G$58),0) -> 0 | H108: =D108 -> LF | I108: =ROUNDUP((E108*$G$58),0) -> 0 | J108: =F108 -> EA
B110: 4-T-N, Full Height=14'
B111: 6" 20ga Metal Stud x 14' at 16" OC | C111: =Z22 -> 9 | D111: LF | E111: =ROUNDUP(C111/1.33,0) -> 7 | F111: EA | G111: =ROUNDUP((C111*$G$58),0) -> 0 | H111: =D111 -> LF | I111: =ROUNDUP((E111*$G$58),0) -> 0 | J111: =F111 -> EA | L111: 2 | M111: =ROUNDUP(C111/(L111*4),0) -> 2
B112: 6" 20ga U-Track x 10' | C112: =C111*2 -> 18 | D112: LF | E112: =ROUNDUP(C112/10,0) -> 2 | F112: EA | G112: =ROUNDUP((C112*$G$58),0) -> 0 | H112: =D112 -> LF | I112: =ROUNDUP((E112*$G$58),0) -> 0 | J112: =F112 -> EA
B113: 6" 20ga Metal Stud Bracing x 8' at 48" OC | C113: =AB16 -> 9 | D113: LF | E113: =ROUNDUP(C113/4,0) -> 3 | F113: EA | G113: =ROUNDUP((C113*$G$58),0) -> 0 | H113: =D113 -> LF | I113: =ROUNDUP((E113*$G$58),0) -> 0 | J113: =F113 -> EA
B115: 4-T-N & 5-T-N, Full Height=12'
B116: 6" 20ga Metal Stud x 12' at 16" OC | C116: =AA22 -> 43 | D116: LF | E116: =ROUNDUP(C116/1.33,0) -> 33 | F116: EA | G116: =ROUNDUP((C116*$G$58),0) -> 0 | H116: =D116 -> LF | I116: =ROUNDUP((E116*$G$58),0) -> 0 | J116: =F116 -> EA | L116: 2 | M116: =ROUNDUP(C116/(L116*4),0) -> 6
B117: 6" 20ga U-Track x 10' | C117: =C116*2 -> 86 | D117: LF | E117: =ROUNDUP(C117/10,0) -> 9 | F117: EA | G117: =ROUNDUP((C117*$G$58),0) -> 0 | H117: =D117 -> LF | I117: =ROUNDUP((E117*$G$58),0) -> 0 | J117: =F117 -> EA
B118: 6" 20ga Metal Stud Bracing x 8' at 48" OC | C118: =AB22-AB16 -> 43 | D118: LF | E118: =ROUNDUP(C118/4,0) -> 11 | F118: EA | G118: =ROUNDUP((C118*$G$58),0) -> 0 | H118: =D118 -> LF | I118: =ROUNDUP((E118*$G$58),0) -> 0 | J118: =F118 -> EA
B120: Soffit, Full Height=12'
...

Sheet Landscaping
A1: Item/Material | B1: Description | C1: Quantities
A2: PLANTS
A3: Mixture of Plants | B3: Sanseviera-Tall, Flowering Annuals-Small, Sweet Potato Vine- Low/Hanging | C3: 7.8
A4: Bird of Paradise | B4: Tall Height | C4: 1
A5: Limelight | B5: Medium Height | C5: 2
A6: ZZ Plant | B6: Medium Height | C6: 2
A7: Golden Pathos | B7: Low Height | C7: 1
A8: Prayer Plant | B8: Low Height | C8: 1
A9: Bird's Nest Fern | B9: Low Height | C9: 1
A10: Sanseviera | B10: Low Height | C10: 1
A12: PLANTER
A13: EXTERIOR
A14: Auroa Clay Outdoor Planters Large | B14: furnished by SB and install by GC | C14: 1
A15: INTERIOR
A16: Parker Pedestal Med Planter-Alabaster, Standard Entry | B16: furnished by SB and install by GC | C16: 1
A17: Flueted Ceramic- TableTop White-Small | B17: furnished by SB and install by GC | C17: 2
A18: Flueted Ceramic- TableTop White-Medium | B18: furnished by SB and install by GC | C18: 2
A20: MISCELLANEOUS
A21: Umbrella Base | B21: furnished by SB and install by GC | C21: 1
A22: Umbrella without Valance | B22: furnished by SB and install by GC | C22: 1
A25: Notes:
A26: Included items that are furnished by Starbucks but to be intalled by GC.
A27: Plant location to be planted on table top counter not specified, so we just used the schedule in the tak-off.
A28: No specified number of plants for Design ID X0004 – Mixture of Plants, so we’re taking off the area for planting.

Sheet Opening
B1: Openings
B3: NOTES:
B4: DOOR
B5: There is a door schedule found on plan, see sheet A601.
B6: Door tag 10190 was not identified on available plans, consider it as in the passage of workroom to restroom/exit corridor.
B7: Hardware set of restrooms are consider and its quanties are 2.
B8: Doors have 1/2" undercut, and non rabbet.
B11: BASE TAKE-OFF
B12: Item | C12: Description | D12: Qty by Unit | E12: MANHOUR | G12: Waste Add-on | I12: Total | L12: Unit Material
D13: NET
B15: Interior Door
B16: Flush Hollow Metal Door, with Frame: SW7047SG, Min: 3 Coats LH Swing
B17: 3'-0''W X 7'-0''W | D17: 1 | I17: =D17 -> 1 | J17: EA | L17: 0
B19: Flush w/ Narrow Lite Panel Hollow Metal Door, Finish: PL0019 with Frame: SW6258-SG, Min: 3 Coats Double Acting
B20: 3'-0''W X 7'-0''W | D20: 2 | I20: =D20 -> 2 | J20: EA | L20: 0
B22: Door Hardware
B23: Hardware Set No. 6
B24: Hanging Items | C24: Manuf.: McKinney - Model: TA2714/MPB79 Hinge MacPro Bearing 4.5 x 4.5 Finish: 626 | D24: 6 | I24: =D24 -> 6 | J24: EA | L24: 0
B25: Securing Devices | C25: Manuf.: Yale Lock - Model: PB5425LN Lock, Shallow Coin Turn, Privacy PB5425LN-693-497 1-3/4 Finish: 626 | D25: 2 | I25: =D25 -> 2 | J25: EA | L25: 0
B26: Closing Devices | C26: Manuf.: Dorma - Model: 8916 Door Closer 8916 AF89P Finish: 689 | D26: 2 | I26: =D26 -> 2 | J26: EA | L26: 0
B27: Protective Trim Units | C27: Manuf.: Rockwood - Model: K1050 B4E Kickplate 8" x 34" Each Side 32D Finish: 630 | D27: 4 | I27: =D27 -> 4 | J27: EA | L27: 0
B28: Accessories | C28: Manuf.: Glynn Johnson - Model: GJ64 Rubber Silencer Finish: Gray | D28: 6 | I28: =D28 -> 6 | J28: EA | L28: 0
B29: Stops and Holders | C29: Manuf.: Rockwood - Model: 473 Door Stop w/ Hook Finish: 626 | D29: 2 | I29: =D29 -> 2 | J29: EA | L29: 0
B31: Hardware Set No. 11 | I31: =D31 -> 0
B32: Traffice Door Package | C32: Manuf: Eliason - Model: SCP8 36" x 84", Finish: as selected by owner | D32: 2 | I32: =D32 -> 2 | J32: EA | L32: 0
B34: Hardware Set No. 15
B35: Hanging Devices | C35: Manuf.: McKinney - Model: TA2714/MPB79 Finish: 626 | D35: 3 | I35: =D35 -> 3 | J35: EA | L35: 0
B36: Securing Devices | C36: Manuf.: Yale Lock - Model: B-PB4540SLNIC Lever Storeroom LC B-PB4540SLN-693-497 1-3/4 Finish: 626 | D36: 1 | I36: =D36 -> 1 | J36: EA | L36: 0
B37: Securing Devices | C37: Manuf.: Falcon Lock - Model: C607 7-Pin Core Combinated "A" Keyway Finish: 626 | D37: 1 | I37: =D37 -> 1 | J37: EA | L37: 0
B38: Closing Devices | C38: Manuf.: Dorma - Model: 8916 Door Closer 8916 AF89P AL Finish: 689 | D38: 1 | I38: =D38 -> 1 | J38: EA | L38: 0
B39: Protective Trim Units | C39: Manuf.: Rockwood - Model: K1050 B4E Kickplate 10" x 2" LDW Finish: 630 | D39: 1 | I39: =D39 -> 1 | J39: EA | L39: 0
B40: Accessories | C40: Manuf.: National Guard - Model: 137NA Weather Strip 17" 36" x 84" Finish: A | D40: 1 | I40: =D40 -> 1 | J40: EA | L40: 0
B41: Stops and Holders | C41: Manuf.: Rockwood - Model: 473 Door Stop w/ Hook Finish: 626 | D41: 1 | I41: =D41 -> 1 | J41: EA | L41: 0
B45: NOTES:
B46: WINDOW
B47: All windows are existing.

Sheet Millwork & Interior Trim
B1: MILLWORK
B3: NOTES:
B4: MILLWORK
B5: There is a casework schedule found on plans. See sheet I603. For items that are shown on plans are trace per enlarged plan and match it quantities.
B6: All items are in count as it specifications are already mentioned and considered.
B7: All items are per SB furnished and only GC are by install, thus no unit material cost are considered.
B8: Highlighted items on sheet I603 are not found on available plans but consider its quantity for reference.
B9: Other non-millwork items falls on finishes.
B12: BASE TAKE-OFF
B13: Item | C13: Description | D13: Qty by Unit | E13: MANHOUR | G13: Waste Add-on | I13: Total | L13: Unit Material
D14: NET
B16: MILLWORK ITEMS SHOWN ON PLANS
B17: BACKBAR | I17: =D17 -> 0 | J17: =G17 -> 0
B18: 22395_Countertop - Hand Sink Low Splash - 15in 380mm | D18: 2 | I18: =D18 -> 2 | J18: EA
B19: x0106_Countertop - Filler Backbar - Variable Length | D19: 1 | I19: =D19 -> 1 | J19: EA
B20: x0108_Countertop - Warming - RF - 92in 2335mm | D20: 1 | I20: =D20 -> 1 | J20: EA
B21: x0107_Countertop - Brew - RF - 80in 2285mm | D21: 1 | I21: =D21 -> 1 | J21: EA
B22: x0105_Countertop - Custom Rounded Wood Edge WD0077 | D22: 1 | I22: =D22 -> 1 | J22: EA
B23: 21928_Countertop - End Cap Backbar | D23: 1 | I23: =D23 -> 1 | J23: EA
B24: x0102_Countertop - CBE Rinse Sink 90lb Ice Bin | D24: 1 | I24: =D24 -> 1 | J24: EA
B25: x0104_Countertop - Custom Rounded Wood Edge WD0077 | D25: 1 | I25: =D25 -> 1 | J25: EA
B26: 21918_Countertop - Filler Frontbar - Variable Length | D26: 1 | I26: =D26 -> 1 | J26: EA
B27: 22353_Countertop - Espresso Frontbar - RF - 14in 3580mm | D27: 1 | I27: =D27 -> 1 | J27: EA
B28: 22354_Countertop - Espresso Shroud - 14in 3580mm | D28: 1 | I28: =D28 -> 1 | J28: EA
B29: 21920_Countertop - Frontbar - 15in 380mm | D29: 2 | I29: =D29 -> 2 | J29: EA
... B42: 11155_Other - Espresso Machine Pump Mount - 10x10in 255x255mm | D42: 1 | I42: =D42 -> 1 | J42: EA
I43: =D43 -> 0
B44: SALES & SEATING | I44: =D44 -> 0
B45: 20352_Cafe - Freestanding Inline 2 Unit Short - 72in 1830mm - Walnut WD0077 | D45: 1 | I45: =D45 -> 1 | J45: EA
B46: 20344_Cafe - Wall Bay on Standard 2 Unit - RF - 92in 2335mm Walnut WD0077 | D46: 1 | I46: =D46 -> 1 | J46: EA
B47: x0101_Cafe - Custom Shelving - WD0077 Walnut | D47: 1 | I47: =D47 -> 1 | J47: EA
B48: 23963_Cafe - Waste and Recycle Station Three Drop - Warm Brown Woodgrain and White PL0030 CP0002 | D48: 1 | I48: =D48 -> 1 | J48: EA
B50: MILLWORK ITEMS NOT SHOWN ON PLANS
B51: CAFE AND CABINET
B52: 21894_Cabinet - Door - 15in 380mm | D52: 7 | I52: =D52 -> 7 | J52: EA
B53: 21895_Cabinet - Door Trash - 15in 380mm | D53: 4 | I53: =D53 -> 4 | J53: EA
B54: 21896_Cabinet - Drawer - 15in 380mm | D54: 1 | I54: =D54 -> 1 | J54: EA
B55: 21905_Cabinet - Door - 30in 760mm | D55: 2 | I55: =D55 -> 2 | J55: EA
B56: 21913_Cabinet - Equipment Mounting Panel | D56: 2 | I56: =D56 -> 2 | J56: EA
B57: 22749_Cabinet - Espresso Pump Mount Panel | D57: 1 | I57: =D57 -> 1 | J57: EA
B58: 22986_Cabinet - Delivery Drawer - 15in 380mm | D58: 3 | I58: =D58 -> 3 | J58: EA
B59: 24517_Cabinet - Adjustable Shelf - 15in 380mm | D59: 14 | I59: =D59 -> 14 | J59: EA
B60: 24520_Cabinet - Adjustable Shelf - 30in 760mm | D60: 9 | I60: =D60 -> 9 | J60: EA
B61: 24525_Cabinet - Back Panel - 15in 380mm | D61: 7 | I61: =D61 -> 7 | J61: EA
B62: 24527_Cabinet - Back Panel - 30in 760mm | D62: 3 | I62: =D62 -> 3 | J62: EA
B63: 24531_Cabinet - Back Panel For Pos - 30in 760mm | D63: 2 | I63: =D63 -> 2 | J63: EA
... B65: 14775_Cafe - Sit Here Table Privacy Panel - Variable Length | D65: 2 | I65: =D65 -> 2 | J65: EA
B69: NOTES:
B70: INTERIOR TRIM
B71: There is a casework schedule found on plans. See sheet I603. For items that are shown on plans are trace per enlarged plan and match it quantities.
B72: On sheet I103 and I106 are the pages used as reference for interior trim takeoff.
B73: All items are per SB furnished and only GC are by install, thus no unit material cost are considered.
B74: Other wood materials are under finishes.
B77: BASE TAKE-OFF
B78: Item | C78: Description | D78: Qty by Unit | E78: MANHOUR | G78: Waste Add-on | I78: Total | L78: Unit Material
D79: NET
B81: INTERIOR TRIM
B82: x0813_Trim - 1 1/2" Wood Trim - WD0077 (7'-6''H) | D82: 2 | I82: =D82 -> 2 | J82: EA
B83: x0815_Trim - 1.5" x Wood Cladding Frame - WD0077 (9'-5 3/4''H) | D83: 2 | I83: =D83 -> 2 | J83: EA
B84: x0800_Trim - 1 1/2" Wood trim - WD0077 | D84: 58.9573 | I84: =D84 -> 58.9573 | J84: LF
B85: x0805_Trim - 1 1/2" Wood Trim - Painted SW7048-F | D85: 23.6056 | I85: =D85 -> 23.6056 | J85: LF
B86: x0810_Trim - 1" x Scuffmaster Painted Solid Wood trim - Harrison Coll 3/SM8005, GOH 34425395 | D86: 34.1755 | I86: =D86 -> 34.1755 | J86: LF
B87: x0812_Trim - 1 1/2" Wood Panel Decorative Trim - WD0077 | D87: 9.0091 | I87: =D87 -> 9.0091 | J87: LF
B88: x0814_Trim - 3/4" Wood Trim - WD0077 | D88: 15.3196 | I88: =D88 -> 15.3196 | J88: LF

Sheet Specialties
B1: Specialties
B3: BASE TAKE-OFF
B5: Item | C5: Description | D5: Qty by Unit | E5: MANHOUR | G5: Waste Add-on | I5: Total
D6: NET
B8: TOILET ACCESSORIES
B9: 16" x 48" Pill Shaped Mirror | C9: West Elm #2997254 | D9: 2 | G9: =D9*H9 -> 0 | H9: 0 | I9: =SUM(D9:G9) -> 2 | J9: EA
B10: 42" x 36" Wide Arch Mirror | C10: West Elm #1682424 | D10: 1 | G10: =D10*H10 -> 0 | H10: 0 | I10: =SUM(D10:G10) -> 1 | J10: EA
B11: Counter Mounted Soap Dispenser - OFCI | D11: 2 | G11: =D11*H11 -> 0 | H11: 0 | I11: =SUM(D11:G11) -> 2 | J11: EA
B12: Recessed Mounted Baby Changing Station | D12: 2 | G12: =D12*H12 -> 0 | H12: 0 | I12: =SUM(D12:G12) -> 2 | J12: EA
B13: Surface Mounted Hand Dryer - OFCI | D13: 2 | G13: =D13*H13 -> 0 | H13: 0 | I13: =SUM(D13:G13) -> 2 | J13: EA
B14: Surface Mounted Horizontal Soap Dispenser - OFCI | D14: 2 | G14: =D14*H14 -> 0 | H14: 0 | I14: =SUM(D14:G14) -> 2 | J14: EA
B15: Surface Mounted Paper Towel Dispenser - OFCI | C15: Half Size - Translucent Gray | D15: 2 | G15: =D15*H15 -> 0 | H15: 0 | I15: =SUM(D15:G15) -> 2 | J15: EA
B16: Surface-Mounted Coat Hook - OFCI | D16: 2 | G16: =D16*H16 -> 0 | H16: 0 | I16: =SUM(D16:G16) -> 2 | J16: EA
B17: Coat Hook Strip - OFCI | D17: 1 | G17: =D17*H17 -> 0 | H17: 0 | I17: =SUM(D17:G17) -> 1 | J17: EA
B18: Hand Dryer Back Panel - OFCI | D18: 2 | G18: =D18*H18 -> 0 | H18: 0 | I18: =SUM(D18:G18) -> 2 | J18: EA
B19: Mirror - BOH - OFCI | D19: 1 | G19: =D19*H19 -> 0 | H19: 0 | I19: =SUM(D19:G19) -> 1 | J19: EA
B20: Mop Rack with 3 Holders - OFCI | D20: 4 | G20: =D20*H20 -> 0 | H20: 0 | I20: =SUM(D20:G20) -> 4 | J20: EA
B22: WIRE SHELVING
B23: Work Room Shelving - OFCI | C23: Size: 36" | D23: 11 | G23: =D23*H23 -> 0 | H23: 0 | I23: =SUM(D23:G23) -> 11 | J23: EA
B24: Work Room Shelving Cart Kit - OFCI | D24: 1 | G24: =D24*H24 -> 0 | H24: 0 | I24: =SUM(D24:G24) -> 1 | J24: EA
B25: Work Room Shelving Posts - OFCI | D25: 11 | G25: =D25*H25 -> 0 | H25: 0 | I25: =SUM(D25:G25) -> 11 | J25: EA
B26: 24" x 18" Base - OFCI | D26: 4 | G26: =D26*H26 -> 0 | H26: 0 | I26: =SUM(D26:G26) -> 4 | J26: EA
B28: WALL PROTECTION
B29: 9'-4"H Metal Corner Guard | C29: Size: 1" Color: Pewter | D29: 3 | G29: =D29*H29 -> 0 | H29: 0 | I29: =SUM(D29:G29) -> 3 | J29: EA
B30: 9'-6"H Metal Corner Guard | C30: Size: 1" Color: Pewter | D30: 12 | G30: =D30*H30 -> 0 | H30: 0 | I30: =SUM(D30:G30) -> 12 | J30: EA
B31: 11'-6"H Metal Corner Guard | C31: Size: 1" Color: Pewter | D31: 1 | G31: =D31*H31 -> 0 | H31: 0 | I31: =SUM(D31:G31) -> 1 | J31: EA
B33: FIRE PROTECTION SPECIALTIES
B34: Fire Extinguisher on Bracket | D34: 1 | G34: =D34*H34 -> 0 | H34: 0 | I34: =SUM(D34:G34) -> 1 | J34: EA
B36: SIGNAGES
B37: Restroom Signage | C37: Size: 1'-4" D x 1'-2 1/2" H Grade II Braille | D37: 1 | G37: =D37*H37 -> 0 | H37: 0 | I37: =SUM(D37:G37) -> 1 | J37: EA
B38: Accessibility Signage | D38: 1 | G38: =D38*H38 -> 0 | H38: 0 | I38: =SUM(D38:G38) -> 1 | J38: EA
B39: Exit Signage | C39: Size: 6" D x 9" H Grade II Braille | D39: 2 | G39: =D39*H39 -> 0 | H39: 0 | I39: =SUM(D39:G39) -> 2 | J39: EA
B41: FURNITURES
B42: Chair - Cafe Daphine Upholstered - OFCI | C42: Color: Black and Caramel Brown Natural WD0035 F0008 | D42: 8 | G42: =D42*H42 -> 0 | H42: 0 | I42: =SUM(D42:G42) -> 8 | J42: EA
B43: Chair - Cafe Hans 2.0 - OFCI | C43: Color: Mottled Grey | D43: 14 | G43: =D43*H43 -> 0 | H43: 0 | I43: =SUM(D43:G43) -> 14 | J43: EA
B44: Chair - Cafe Peggy - OFCI | C44: Color: Black WD0035 | D44: 14 | G44: =D44*H44 -> 0 | H44: 0 | I44: =SUM(D44:G44) -> 14 | J44: EA
B45: Chair - Cafe Peggy Upholstered - OFCI | C45: Color: Walnut and Caramel Brown Natural WD0077 F0008 | D45: 9 | G45: =D45*H45 -> 0 | H45: 0 | I45: =SUM(D45:G45) -> 9 | J45: EA
B46: Chair - Lounge Hans 2.0 - OFCI | C46: Color: Mottled Grey | D46: 6 | G46: =D46*H46 -> 0 | H46: 0 | I46: =SUM(D46:G46) -> 6 | J46: EA
B47: Chair - Lounge Lottie - OFCI | C47: Color: Banker Saddle | D47: 4 | G47: =D47*H47 -> 0 | H47: 0 | I47: =SUM(D47:G47) -> 4 | J47: EA
B48: Chair - Lounge Moon- OFCI | C48: Color: Black and Caramel Brown Natural MT0028 F0008 | D48: 6 | G48: =D48*H48 -> 0 | H48: 0 | I48: =SUM(D48:G48) -> 6 | J48: EA
B49: Chair - Managers Workstation- OFCI | C49: Steelcase Series One Armless | D49: 1 | G49: =D49*H49 -> 0 | H49: 0 | I49: =SUM(D49:G49) -> 1 | J49: EA
B50: Chair - Stool - Counter Height Peggy Upholstered- OFCI | C50: Color: Walnut and Caramel Brown Natural WD0077 F0008 | D50: 12 | G50: =D50*H50 -> 0 | H50: 0 | I50: =SUM(D50:G50) -> 12 | J50: EA
B51: Chair - Stool Bar Height Mater- OFCI | C51: Color: Dark Stained Oak | D51: 8 | G51: =D51*H51 -> 0 | H51: 0 | I51: =SUM(D51:G51) -> 8 | J51: EA
B52: Chair - Stool Counter Height Peggy- OFCI | C52: Color: Black WD0035 | D52: 6 | G52: =D52*H52 -> 0 | H52: 0 | I52: =SUM(D52:G52) -> 6 | J52: EA
B53: Desk - Managers Workstation- OFCI | C53: Size: 48"x24"27" | D53: 1 | G53: =D53*H53 -> 0 | H53: 0 | I53: =SUM(D53:G53) -> 1 | J53: EA
B54: Desk - Managers Workstation Shelves- OFCI | C54: Size: 48"x24"27" | D54: 1 | G54: =D54*H54 -> 0 | H54: 0 | I54: =SUM(D54:G54) -> 1 | J54: EA
B55: File Mobile Pedestal with Cushion and Lock- OFCI | D55: 1 | G55: =D55*H55 -> 0 | H55: 0 | I55: =SUM(D55:G55) -> 1 | J55: EA
B56: Hamilton Leather Sofa- OFCI | C56: West Elm - Burnt Sienna #5942664 | D56: 2 | G56: =D56*H56 -> 0 | H56: 0 | I56: =SUM(D56:G56) -> 2 | J56: EA
B57: Managers Desk Cart- OFCI | C57: Size: 24"x20" | D57: 1 | G57: =D57*H57 -> 0 | H57: 0 | I57: =SUM(D57:G57) -> 1 | J57: EA
B58: Organic Modular Table- OFCI | C58: West Elm - Large, Dark Walnut #2439505 | D58: 2 | G58: =D58*H58 -> 0 | H58: 0 | I58: =SUM(D58:G58) -> 2 | J58: EA
B59: Storytelling Accessories Package | D59: 1 | G59: =D59*H59 -> 0 | H59: 0 | I59: =SUM(D59:G59) -> 1 | J59: EA
B60: Table - Accessible Metal with Tapered Legs - OFCI | C60: Size: 36"x24" Color: Black MT0028 | D60: 1 | G60: =D60*H60 -> 0 | H60: 0 | I60: =SUM(D60:G60) -> 1 | J60: EA
B61: Table - Base Accessible Post Leg Square - OFCI | C61: Color: Flat Black MT0028 | D61: 2 | G61: =D61*H61 -> 0 | H61: 0 | I61: =SUM(D61:G61) -> 2 | J61: EA
B62: Table - Base Bar Height POV 463 - OFCI | C62: Color: Nougat | D62: 4 | G62: =D62*H62 -> 0 | H62: 0 | I62: =SUM(D62:G62) -> 4 | J62: EA
B63: Table - Base Cafe Height Bottle - OFCI | C63: Color: Flat Black MT0028 | D63: 10 | G63: =D63*H63 -> 0 | H63: 0 | I63: =SUM(D63:G63) -> 10 | J63: EA
B64: Table - Base Continental Height Bottle - OFCI | C64: Color: Flat Black MT0028 | D64: 3 | G64: =D64*H64 -> 0 | H64: 0 | I64: =SUM(D64:G64) -> 3 | J64: EA
B65: Table - Base Fixed T Base End - OFCI | C65: Size: 32" Color: Flat Black MT0028 | D65: 1 | G65: =D65*H65 -> 0 | H65: 0 | I65: =SUM(D65:G65) -> 1 | J65: EA
B66: Table - Cafe Metal Pedestal Base Square - OFCI | C66: Size: 24" Color: Black MT0028 | D66: 6 | G66: =D66*H66 -> 0 | H66: 0 | I66: =SUM(D66:G66) -> 6 | J66: EA
B67: Table - Community Counter Height Angle Base - 12 Seat - OFCI | C67: Color: Power Walnut WD0077 | D67: 1 | G67: =D67*H67 -> 0 | H67: 0 | I67: =SUM(D67:G67) -> 1 | J67: EA
B68: Table - Console Table - OFCI | C68: West Elm - Parker Marble Console 60" Marble & Walnut SKU: 6553487 | D68: 1 | G68: =D68*H68 -> 0 | H68: 0 | I68: =SUM(D68:G68) -> 1 | J68: EA
B69: Table - Occasional Cocktail Cameron - OFCI | C69: Color: Flat Black MT0028 | D69: 3 | G69: =D69*H69 -> 0 | H69: 0 | I69: =SUM(D69:G69) -> 3 | J69: EA
B70: Table - Occasional Side Wing - OFCI | C70: Color: Black WD0035 | D70: 6 | G70: =D70*H70 -> 0 | H70: 0 | I70: =SUM(D70:G70) -> 6 | J70: EA
B71: Table - Occassional Coffee Organic Modular Table - OFCI | C71: West Elm - Small, Dark Walnut #8066175 | D71: 2 | G71: =D71*H71 -> 0 | H71: 0 | I71: =SUM(D71:G71) -> 2 | J71: EA
... B76: Table - Top Variable Length - OFCI | C76: Color: Flat Black MT0028 | D76: 1 | G76: =D76*H76 -> 0 | H76: 0 | I76: =SUM(D76:G76) -> 1 | J76: EA
B78: MISCELLANEOUS
B79: 15" 5 Comp Locker - OFCI | C79: Size: 15" | D79: 2 | G79: =D79*H79 -> 0 | H79: 0 | I79: =SUM(D79:G79) -> 2 | J79: EA
B80: 93" Power Strip - OFCI | D80: 2 | G80: =D80*H80 -> 0 | H80: 0 | I80: =SUM(D80:G80) -> 2 | J80: EA
B81: Partner Work Center - OFCI | D81: 1 | G81: =D81*H81 -> 0 | H81: 0 | I81: =SUM(D81:G81) -> 1 | J81: EA
B85: NOTES:
B86: =B1 -> Specialties
B87: No Toilet Accessory Schedule provided.
B88: Existing Toilet Accessory not considered in the proposal.
B89: Accessibility Signage Specs not given in plan.
B90: No manufacturer and model given for Fire Extinguishers and Toilet Accessories.
B91: Horizontal Soap Dispenser was not listed under specialtiy equipment at sheet I601, it was included in the proposal. Considered as OFCI, the same with other accessories listed.
B92: Considered 11 counts of Work Room Shelving (6 counts in schedule).
B93: West Elm Mirror Manufacturer and Model at sheet I602
B94: Considered Furnitures and Shelving in the Proposal

Sheet Wood Framing
B2: NOTES:
B3: Rough Framing
B4: Assumed SYP#2 Lumber Specie
B5: Considered all blockings to be FRT (A101|Gen. Notes Item B)
B6: New Walls are specified as Metal Studs per schedule at A101
B7: Assumed 2x6 Blockings for Wall Blockings not specified in Plan
B8: 1x4 FRT blocking at openings per detail 5|I509
B9: Considered 3/4" Plywood backing at Details 2|I502 & 2|I503
B10: Considere 2x10 FRT blocking per detail 2 | I504
B12: 1.A Typical Wall Framing Takeoff
B13: DESCRIPTION | C13: Total LF/QTY (Planswift data and rounded up) | D13: OC Spacing (in.) Use 16"OC, UNO | E13: BOTTOM AND TOP PLATE, BLOCKING (LF)
E14: 2 x 6 FRT | F14: 2x4 FRT | G14: 1x4 FRT | H14: 2x10 FRT
B15: 1F
B16: 2x6 FRT Blocking | C16: 125 | E16: 181
B17: 1x4 FRT Wood Blocking (5|I509) | C17: 10 | G17: =+$C17 -> 10
B18: 1x4x9' FRT Wood Blocking (5|I509) | C18: 4 | G18: =+C18*9 -> 36
B19: 1x4x10' FRT Wood Blocking (5|I509) | C19: 2 | G19: =+C19*10 -> 20
B20: 2x4x3' FRT Vert.Blocking (6|1501) | C20: 20 | F20: =+C20*3 -> 60
B21: 2x10 FRT Blocking | C21: 20 | H21: =+$C21 -> 20
C23: =B15&" - SUB TOTAL:" -> 1F - SUB TOTAL: | E23: =ROUNDUP(SUM(E16:E22),0) -> 181 | F23: =ROUNDUP(SUM(F16:F22),0) -> 60 | G23: =ROUNDUP(SUM(G16:G22),0) -> 66 | H23: =ROUNDUP(SUM(H16:H22),0) -> 20
B25: 1.B Structural Wall Framing Takeoff
B26: DESCRIPTION | C26: Total LF/QTY (Planswift data and rounded up) | D26: Sheathing Height (FT) | E26: SHEATHING (4'x8') (SF)
E27: 3/4" x 4' x 8' Plywood
B28: 1F
B29: 3/4" Plywood Backing (H=8') (2|I502) | C29: 10 | D29: 8 | E29: =+C29*D29 -> 80
B30: 3/4" Plywood Backing (2|I503) | C30: 31 | E30: =+C30 -> 31
C32: =B28&" - SUB TOTAL:" -> 1F - SUB TOTAL: | E32: =ROUNDUP(SUM(E28:E31),0) -> 111
B34: M A T E R I A L S U M M A R Y | F34: Studs Specie | G34: SYP#2
B35: Item | C35: Description | D35: Qty | E35: Unit
B36: LUMBER
B37: Misc. Blockings
B38: 2" x 6" x 16' SYP#2 FRT | C38: Blocking at Wall | D38: =ROUNDUP(+E23/16,) -> 12 | E38: EA
B39: 2" x 4" x 16' SYP#2 FRT | C39: Blocking at Wall | D39: =+ROUNDUP(F23/16,) -> 4 | E39: EA
B40: 2" x 10" x 16' SYP#2 FRT | C40: Blocking at Wall | D40: =+ROUNDUP(H23/16,) -> 2 | E40: EA
B41: 1" x 4" x 16' SYP#2 FRT | C41: Blocking at Door Headers & Jambs | D41: =+ROUNDUP(G23/16,) -> 5 | E41: EA
B42: 3/4" x 4' x 8' Plywood | C42: Plywood Backing | D42: =+ROUNDUP(E32/32,0) -> 4 | E42: EA

Sheet Interior Painting & Finishes
B2: NOTES:
B3: Paint and interior finish specifications per print I603
B4: One coat of primer and two coats of paint are considered for all drywall and open to structure.
B5: Two coats of paint are considered for all existing drywall.
B6: One coat of primer is considered for FRP surfaces.
G8: Paint Coverages Area/Gallon
B9: BASE TAKE-OFF | G9: Primer | H9: 250SF/gal
G10: Paint | H10: 300SF/gal
B12: WALL FINISHES (INTERIOR) | E12: Length | F12: Height | G12: Sides | H12: Finish
B13: Brick, x0407 | C13: =E13*F13*G13 -> 156 | D13: SF | E13: 13 | F13: 12 | G13: 1
B14: Brick, x0407 | C14: =E14*F14*G14 -> 266 | D14: SF | E14: 14 | F14: 19 | G14: 1
B15: Brick, x0407 | C15: =E15*F15*G15 -> 234 | D15: SF | E15: 13 | F15: 18 | G15: 1
B16: Wall Cladding, MAD100 | C16: =E16*F16*G16 -> 105 | D16: SF | E16: 21 | F16: 5 | G16: 1
B17: Wall Cladding, MAD100 | C17: =E17*F17*G17 -> 40 | D17: SF | E17: 4 | F17: 10 | G17: 1
B18: Wall Cladding, MAD100 | C18: =E18*F18*G18 -> 252 | D18: SF | E18: 21 | F18: 12 | G18: 1
B19: Wall Cladding, MAD100 | C19: =E19*F19*G19 -> 48 | D19: SF | E19: 16 | F19: 3 | G19: 1
B20: Wall Cladding, MAD100 | C20: =E20*F20*G20 -> 176 | D20: SF | E20: 16 | F20: 11 | G20: 1
B21: Wall Cladding, MAD100-V | C21: =E21*F21*G21 -> 45 | D21: SF | E21: 15 | F21: 3 | G21: 1
B22: Wall Cladding, MAD200 | C22: =E22*F22*G22 -> 108 | D22: SF | E22: 18 | F22: 6 | G22: 1
B23: Wall Covering, X0403 | C23: =E23*F23*G23 -> 221 | D23: SF | E23: 17 | F23: 13 | G23: 1
B24: Wall Covering, X0403 | C24: =E24*F24*G24 -> 440 | D24: SF | E24: 55 | F24: 8 | G24: 1
... B31: Primer on FRP | C31: =E31*F31*G31 -> 1584 | D31: SF | E31: 176 | F31: 9 | G31: 1
B33: CEILING FINISHES | E33: Length | F33: Height
B34: PT on Existing Gypsum, SW7030 | C34: 122 | D34: SF
B35: PT on Gypsum, SW9090-F | C35: 102 | D35: SF
B36: PT on Gypsum, SW9090-ES | C36: 653 | D36: SF
B37: PT on Gypsum, SW9090-ES | C37: =E37*F37 -> 175 | D37: SF | E37: 35 | F37: 5
B38: PT on Gypsum, SW9090-ES | C38: =E38*F38 -> 318 | D38: SF | E38: 53 | F38: 6
B39: PT on Gypsum, SW7030 | C39: 113 | D39: SF
B40: PT on Gypsum, SW7030 | C40: =E40*F40 -> 29 | D40: SF | E40: 29 | F40: 1
B41: PT on Gypsum, SW7048 | C41: =E41*F41 -> 51 | D41: SF | E41: 51 | F41: 1
B42: PT on Gypsum, SW7048 | C42: =E42*F42 -> 255 | D42: SF | E42: 51 | F42: 5
B43: PT on Gypsum, Undefined | C43: =E43*F43 -> 40 | D43: SF | E43: 10 | F43: 4
B44: Paint to Open to Structure, SW7048 | C44: 904 | D44: SF
B45: Acoustical Baffle x0205 | C45: 174 | D45: SF
B46: Acoustical Baffle x0206 | C46: 748 | D46: SF
B47: Coffered Panel | C47: 174 | D47: SF
B48: 2x4 ACT Tile | C48: 552 | D48: SF
B49: ACT Wall Moulding | C49: 173 | D49: LF
B51: DOOR AND DOOR FRAME | E51: no. of Doors | F51: Height | G51: Width | H51: Frame Perimeter
B52: 4' x 7' Exterior Single Leaf Door
B53: SW7047 | C53: =E53*F53*G53*2 -> 56 | D53: SF | E53: 1 | F53: 7 | G53: 4
B54: 3' x 7' Interior Single Leaf Door
B55: SW7047 | C55: =E55*F55*G55*2 -> 126 | D55: SF | E55: 3 | F55: 7 | G55: 3
B56: 3' x 7' Interior Single Leaf Door
B57: SW6258 | C57: =E57*F57*G57*2 -> 84 | D57: SF | E57: 2 | F57: 7 | G57: 3
B59: MISCELLANEOUS ITEMS | E59: Qty | F59: Height
B60: METAL
B61: 1" Metal Angle Corner Guard | C61: =E61*F61 -> 12 | D61: LF | E61: 1 | F61: 12
B62: 1" FRP Corner Guard | C62: =E62*F62 -> 120 | D62: LF | E62: 12 | F62: 10
B64: SUMMARY
B65: ITEM | C65: DESCRIPTION | D65: QTY | E65: UNIT | F65: WASTE ADD-ON | H65: Typical Productivity | I65: UNIT | J65: MH/UNIT | K65: TOTAL MANHOUR
B66: INTERIOR FINISHES | F66: 1 | M66: Duration Target | N66: 15 | O66: days
B67: Brick, x0407 | C67: THIN BRICK CLADDING - EL DORADO STONE - TUNDRABRICK RIVERBED - LIGHT BUFF MORTAR | D67: =SUM(C13:C15) -> 656 | E67: =D31 -> SF | F67: =ROUNDUP((D67*$F$66),0) -> 656 | G67: =E67 -> SF | H67: 7 | I67: SF/HR | J67: =1/H67 -> 0.14285714 | K67: =ROUNDUP(J67*F67,0) -> 94 | M67: Workday | N67: 8 | O67: hours
B68: Wall Cladding, MAD100 | C68: WOOD - WALNUT | D68: =SUM(C16:C20) -> 621 | E68: SF | F68: =ROUNDUP((D68*$F$66),0) -> 621 | G68: =E68 -> SF | H68: 12 | I68: SF/HR | J68: =1/H68 -> 0.083333333 | K68: =ROUNDUP(J68*F68,0) -> 52 | M68: Total Hour | N68: =SUM(K67:K81) -> 461 | O68: manhours
B69: Wall Cladding, MAD100-V | C69: WOOD - BLACK - PLANK - VERTICAL | D69: =SUM(C21) -> 45 | E69: SF | F69: =ROUNDUP((D69*$F$66),0) -> 45 | G69: =E69 -> SF | H69: 11 | I69: SF/HR | J69: =1/H69 -> 0.090909091 | K69: =ROUNDUP(J69*F69,0) -> 5 | M69: Crew Size | N69: =ROUNDUP(N68/(N66*N67),0) -> 4 | O69: workers
B70: Wall Cladding, MAD200 | C70: WOOD - BLACK - ROUNDED SLAT - VERTICAL | D70: =SUM(C22) -> 108 | E70: SF | F70: =ROUNDUP((D70*$F$66),0) -> 108 | G70: =E70 -> SF | H70: 9 | I70: SF/HR | J70: =1/H70 -> 0.11111111 | K70: =ROUNDUP(J70*F70,0) -> 12
B71: Wall Covering, X0403 | C71: WALL COVERING - MOMENTUM - CAMBRIAN - SLATE | D71: =SUM(C23:C24) -> 661 | E71: SF | F71: =ROUNDUP((D71*$F$66),0) -> 661 | G71: =E71 -> SF | H71: 30 | I71: SF/HR | J71: =1/H71 -> 0.033333333 | K71: =ROUNDUP(J71*F71,0) -> 23
B72: Wall Covering, X0811 | C72: 3/4" WOOD VENEER PANEL | D72: =SUM(C25) -> 70 | E72: SF | F72: =ROUNDUP((D72*$F$66),0) -> 70 | G72: =E72 -> SF | H72: 7 | I72: SF/HR | J72: =1/H72 -> 0.14285714 | K72: =ROUNDUP(J72*F72,0) -> 10
B73: Wall Projection | C73: FRP - White | D73: =SUM(C31) -> 1584 | E73: SF | F73: =ROUNDUP((D73*$F$66),0) -> 1584 | G73: =E73 -> SF | H73: 20 | I73: SF/HR | J73: =1/H73 -> 0.05 | K73: =ROUNDUP(J73*F73,0) -> 80
B74: Acoustical Baffle x0205 | C74: SOFTSPAN 24" ACOUSTICAL BAFFLE SYSTEM W/ PERIMETER BEAMS/CORNERS AND COFFERED PANELS, SOFT SOUND WOOD TEXTURE ACOUSTIC PET, AMERICAN WALNUT | D74: =C45 -> 174 | E74: SF | F74: =ROUNDUP((D74*$F$66),0) -> 174 | G74: =E74 -> SF | H74: 9 | I74: SF/HR | J74: =1/H74 -> 0.11111111 | K74: =ROUNDUP(J74*F74,0) -> 20
B75: Acoustical Baffle x0206 | C75: SOFTSPAN 48" ACOUSTICAL BAFFLE SYSTEM W/ PERIMETER BEAMS/CORNERS, SOFT SOUND WOOD TEXTURE ACOUSTIC PET, AMERICAN WALNUT | D75: =C46 -> 748 | E75: SF | F75: =ROUNDUP((D75*$F$66),0) -> 748 | G75: =E75 -> SF | H75: 9 | I75: SF/HR | J75: =1/H75 -> 0.11111111 | K75: =ROUNDUP(J75*F75,0) -> 84
B76: 2x4 ACT Tile | C76: ARMSTRONG - OPTIMA HEALTH ZONE 3115 (WHITE), SQUARE LAY-IN 15/16 W/GRID TO MATCH | D76: =C48 -> 552 | E76: SF | F76: =ROUNDUP((D76*$F$66),0) -> 552 | G76: =E76 -> SF | H76: 15 | I76: SF/HR | J76: =1/H76 -> 0.066666667 | K76: =ROUNDUP(J76*F76,0) -> 37
C77: ARMSTRONG PRELUDE XL MAIN RUNNERS 12 FT | D77: =ROUNDUP(D76/4/12,0) -> 12 | E77: EA | F77: =ROUNDUP((D77*$F$66),0) -> 12 | G77: =E77 -> EA | H77: 7 | I77: EA/HR | J77: =1/H77 -> 0.14285714 | K77: =ROUNDUP(J77*F77,0) -> 2
C78: ARMSTRONG 4 FOOT TEES | D78: =ROUNDUP(D76/4/2,0) -> 69 | E78: EA | F78: =ROUNDUP((D78*$F$66),0) -> 69 | G78: =E78 -> EA | H78: 7 | I78: EA/HR | J78: =1/H78 -> 0.14285714 | K78: =ROUNDUP(J78*F78,0) -> 10
C79: 7/8" X 7/8" WALL MOLDING 12 FT. | D79: =C49 -> 173 | E79: EA | F79: =ROUNDUP((D79*$F$66),0) -> 173 | G79: =E79 -> EA | H79: 7 | I79: EA/HR | J79: =1/H79 -> 0.14285714 | K79: =ROUNDUP(J79*F79,0) -> 25
C80: HANGER WIRE 12GA, 12FT. | D80: =D77*4 -> 48 | E80: EA | F80: =ROUNDUP((D80*$F$66),0) -> 48 | G80: =E80 -> EA | H80: 7 | I80: EA/HR | J80: =1/H80 -> 0.14285714 | K80: =ROUNDUP(J80*F80,0) -> 7
B82: INTERIOR PAINT | M82: Duration Target | N82: 5 | O82: days
B83: Primer, 1 Coat | M83: Workday | N83: 8 | O83: hours
B84: to Gypsum Board | C84: CP-1 | D84: =SUM(C26:C31,C35:C42) -> 4517 | E84: SF | F84: =ROUNDUP((D84*$F$66),0) -> 4517 | G84: =E84 -> SF | H84: 180 | I84: SF/HR | J84: =1/H84 -> 0.0055555556 | K84: =ROUNDUP(J84*F84,0) -> 26 | M84: Total Hour | N84: =SUM(K84:K110) -> 116 | O84: manhours
B85: to Open to Structure | C85: CP-1 | D85: =C44 -> 904 | E85: SF | F85: =ROUNDUP((D85*$F$66),0) -> 904 | G85: =E85 -> SF | H85: 100 | I85: SF/HR | J85: =1/H85 -> 0.01 | K85: =ROUNDUP(J85*F85,0) -> 10 | M85: Crew Size | N85: =ROUNDUP(N84/(N82*N83),0) -> 3 | O85: workers
B87: Paint Finish, 2 Coats
B88: Walls
B89: PT on Gypsum Board | C89: ANEW GREY, SW7030, Eggshell Finish | D89: =SUM(C26) -> 189 | E89: SF | F89: =ROUNDUP((D89*$F$66),0) -> 189 | G89: =E89 -> SF | H89: 80 | I89: SF/HR | J89: =1/H89 -> 0.0125 | K89: =ROUNDUP(J89*F89,0) -> 3
B90: PT on Gypsum Board | C90: URBANE BRONZE, SW7048, Flat Finish | D90: =SUM(C27:C30) -> 1048 | E90: SF | F90: =ROUNDUP((D90*$F$66),0) -> 1048 | G90: =E90 -> SF | H90: 80 | I90: SF/HR | J90: =1/H90 -> 0.0125 | K90: =ROUNDUP(J90*F90,0) -> 14
B92: Ceilings
B93: PT on Gypsum Board | C93: ANEW GREY, SW7030, Eggshell Finish | D93: =SUM(C34,C39:C40) -> 264 | E93: SF | F93: =ROUNDUP((D93*$F$66),0) -> 264 | G93: =E93 -> SF | H93: 75 | I93: SF/HR | J93: =1/H93 -> 0.013333333 | K93: =ROUNDUP(J93*F93,0) -> 4
B94: PT on Gypsum Board | C94: CARAIBE, SW9090, Eggshell Finish | D94: =SUM(C36:C38) -> 1146 | E94: SF | F94: =ROUNDUP((D94*$F$66),0) -> 1146 | G94: =E94 -> SF | H94: 75 | I94: SF/HR | J94: =1/H94 -> 0.013333333 | K94: =ROUNDUP(J94*F94,0) -> 16
B95: PT on Gypsum Board | C95: CARAIBE, SW9090, Flat Finish | D95: =SUM(C35) -> 102 | E95: SF | F95: =ROUNDUP((D95*$F$66),0) -> 102 | G95: =E95 -> SF | H95: 75 | I95: SF/HR | J95: =1/H95 -> 0.013333333 | K95: =ROUNDUP(J95*F95,0) -> 2
B96: PT on Gypsum Board | C96: URBANE BRONZE, SW7048, Flat Finish | D96: =SUM(C41:C42) -> 306 | E96: SF | F96: =ROUNDUP((D96*$F$66),0) -> 306 | G96: =E96 -> SF | H96: 75 | I96: SF/HR | J96: =1/H96 -> 0.013333333 | K96: =ROUNDUP(J96*F96,0) -> 5
B97: PT on Gypsum Board | C97: UNDEFINED | D97: =SUM(C43) -> 40 | E97: SF | F97: =ROUNDUP((D97*$F$66),0) -> 40 | G97: =E97 -> SF | H97: 75 | I97: SF/HR | J97: =1/H97 -> 0.013333333 | K97: =ROUNDUP(J97*F97,0) -> 1
B98: Paint on Open to Structure | C98: URBANE BRONZE, SW7048, Flat Finish | D98: =C44 -> 904 | E98: SF | F98: =ROUNDUP((D98*$F$66),0) -> 904 | G98: =E98 -> SF | H98: 60 | I98: SF/HR | J98: =1/H98 -> 0.016666667 | K98: =ROUNDUP(J98*F98,0) -> 16
B100: DOORS
B101: 3' x 7' Interior Single Leaf Door | C101: SW7047, Semi-Gloss Finish | D101: =E55 -> 3 | E101: EA | F101: =ROUNDUP((D101*$F$66),0) -> 3 | G101: =E101 -> EA | H101: 0.75 | I101: EA/HR | J101: =1/H101 -> 1.3333333 | K101: =ROUNDUP(J101*F101,0) -> 4
B102: 4' x 7' Interior Single Leaf Door | C102: SW7047, Semi-Gloss Finish | D102: =E53 -> 1 | E102: EA | F102: =ROUNDUP((D102*$F$66),0) -> 1 | G102: =E102 -> EA | H102: 0.75 | I102: EA/HR | J102: =1/H102 -> 1.3333333 | K102: =ROUNDUP(J102*F102,0) -> 2
B104: DOORS FRAMES
B105: 3' x 7' Interior Single Leaf Door Frame | C105: SW7047, Semi-Gloss Finish | D105: =E55 -> 3 | E105: EA | F105: =ROUNDUP((D105*$F$66),0) -> 3 | G105: =E105 -> EA | H105: 0.5 | I105: EA/HR | J105: =1/H105 -> 2 | K105: =ROUNDUP(J105*F105,0) -> 6
B106: 4' x 7' Interior Single Leaf Door Frame | C106: SW7047, Semi-Gloss Finish | D106: =E53 -> 1 | E106: EA | F106: =ROUNDUP((D106*$F$66),0) -> 1 | G106: =E106 -> EA | H106: 0.5 | I106: EA/HR | J106: =1/H106 -> 2 | K106: =ROUNDUP(J106*F106,0) -> 2
B107: 3' x 7' Interior Single Leaf Door Frame | C107: SW6258, Semi-Gloss Finish | D107: =E57 -> 2 | E107: EA | F107: =ROUNDUP((D107*$F$66),0) -> 2 | G107: =E107 -> EA | H107: 0.5 | I107: EA/HR | J107: =1/H107 -> 2 | K107: =ROUNDUP(J107*F107,0) -> 4
B109: MISCELLANEOUS ITEMS
B110: 1" Metal Angle Corner Guard | C110: URBANE BRONZE, SW7048, Flat Finish | D110: =C61 -> 12 | E110: LF | F110: =ROUNDUP((D110*$F$66),0) -> 12 | G110: =E110 -> LF | H110: 20 | I110: LF/HR | J110: =1/H110 -> 0.05 | K110: =ROUNDUP(J110*F110,0) -> 1

Sheet HM Frame Door
B2: Description | C2: QTY (EA) | E2: Unit Material | F2: Total Material | G2: Unit Labor | H2: Total Labor
B4: DOORS
B5: TYPE D1, HM FRAME - 3'-0' x 7'-0' | C5: 7 | E5: 0 | F5: =C5*E5 -> 0 | G5: 0 | H5: =C5*G5 -> 0
B6: TYPE D2, HM FRAME - 16'-0' x 14'-0' | C6: 1 | E6: 0 | F6: =C6*E6 -> 0 | G6: 0 | H6: =C6*G6 -> 0
B7: TYPE D2, HM FRAME - 20'-0' x 14'-0' | C7: 2 | E7: 0 | F7: =C7*E7 -> 0 | G7: 0 | H7: =C7*G7 -> 0

Sheet Exterior Siding
B1: Starbucks - Exterior Siding Takeoffs
B2: 1620 S University Dr, Fort Worth, TX 76107
B3: EXTERIOR SIDINGS
B5: NOTE:
B6: Exterior Siding
B7: Only Patching and repair area were considered in takeoffs.
B8: Brick Veneer considered in the takeoffs as per plan.
B11: EXTERIOR- Windows and Doors
B12: Description/Type Windows | C12: Width (FT') | D12: Height (FT') | E12: QTY | F12: LF w/o Sill | G12: Total LF Surround | H12: Total LF Top | I12: Total LF Sill | J12: Total Window/Door Tape
F13: =G13-I13 -> 0 | G13: =E13*(D13+D13+C13+C13) -> 0 | H13: =C13*E13 -> 0 | I13: =C13*E13 -> 0 | J13: =G13 -> 0
B14: SUM | E14: =SUM(E13) -> 0 | F14: =SUM(F13) -> 0 | G14: =SUM(G13) -> 0 | H14: =SUM(H13) -> 0 | I14: =SUM(I13) -> 0 | J14: =SUM(J13) -> 0
B15: Description/Type Doors | C15: Width (FT') | D15: Height (FT') | E15: QTY | F15: SF | G15: Total LF Surround | H15: Total LF Top | I15: Total LF Threshold | J15: Total Window/Door Tape
F16: =C16*D16*E16 -> 0 | G16: =E16*(D16+D16+C16) -> 0 | H16: =C16*E16 -> 0 | I16: =C16*E16 -> 0 | J16: =G16 -> 0
B17: SUM | E17: =SUM(E16) -> 0 | F17: =SUM(F16) -> 0 | G17: =SUM(G16) -> 0 | H17: =SUM(H16) -> 0 | I17: =SUM(I16) -> 0 | J17: =SUM(J16) -> 0
B19: Sidings | C19: Size / O.C. Spacing | D19: QTY | E19: UNIT
B20: Veneer Siding
B21: Brick Veneer | C21: Patching and Repair | D21: =104.29+58.98 -> 163.27 | E21: SF | I21: =ROUNDUP(D21/1,0) -> 164
B24: Exterior Siding
B25: Siding
B26: Veneer Siding
B27: =B21 -> Brick Veneer | C27: =C21 -> Patching and Repair | D27: =ROUNDUP(D21,0) -> 164 | E27: SF

Sheet Exterior Painting
B1: BASE TAKEOFF
B2: Project: | C2: Waynesville
B3: Address: | C3: 200 Fleetwood Drive, Waynesville, Missouri 65583
B4: Date of Plans | C4: 45733
B5: Date of Bid | C5: 45965
B7: EXTERIOR FINISHES
B8: Exterior Patio Railing Finishes, 2 Coats Stain
B9: 3' H Patio Railing (at Patio)(Painted)(x2) | C9: =PRODUCT(E9:G9) -> 94.44 | D9: LF | E9: 2 | F9: 47.22 | H9: =F9*E9*3 -> 283.32
B11: Exterior Patio Railings | C11: =SUM(C8:C10) -> 94.44 | D11: LF
B12: Exterior Patio Post Finishes, Primer + 2 Coats Paint
B13: 3" Dia Patio Post (Painted)(2x) | C13: =PRODUCT(E13:G13) -> 25.02 | D13: LF | E13: 2 | F13: =4.17*3 -> 12.51 | H13: =C13*0.125 -> 3.1275
B14: 4-1/2" Dia Patio Post (Painted)(2x) | C14: =PRODUCT(E14:G14) -> 60 | D14: LF | E14: 2 | F14: =10*3 -> 30 | H14: =C14*0.1875 -> 11.25
H15: =H13+H14 -> 14.3775
B16: Exterior Patio Post | C16: =C14+C13 -> 85.02 | D16: LF
B20: NOTES:
B21: Painting:
B22: Two coats of stain paint are considered for the Exterior Patio Railings.
B23: One coat of primer and two coats of paint are considered for the Exterior Patio Posts.
B24: As per Key Note 6 , Patio Railing will be restained wood SW3524.
B25: As per Key Note 6 , Patio Post will be repainted SW7048.
